{
 "cells": [
  {
   "cell_type": "code",
   "execution_count": 1,
   "metadata": {},
   "outputs": [],
   "source": [
    "from battlehack20 import Game\n",
    "from battlehack20.engine.container.instrument import Instrument\n",
    "from RestrictedPython import compile_restricted\n",
    "import dis\n",
    "import math\n",
    "from types import CodeType\n",
    "import faulthandler\n",
    "from types import SimpleNamespace"
   ]
  },
  {
   "cell_type": "code",
   "execution_count": 2,
   "metadata": {},
   "outputs": [],
   "source": [
    "faulthandler.enable()"
   ]
  },
  {
   "cell_type": "code",
   "execution_count": 80,
   "metadata": {},
   "outputs": [],
   "source": [
    "examplefuncs = \"\"\"\n",
    "import random\n",
    "\n",
    "\n",
    "# This is an example bot written by the developers!\n",
    "# Use this to help write your own code, or run it against your bot to see how well you can do!\n",
    "\n",
    "DEBUG = 1\n",
    "def dlog(str):\n",
    "    if DEBUG > 0:\n",
    "        log(str)\n",
    "\n",
    "\n",
    "def check_space_wrapper(r, c, board_size):\n",
    "    # check space, except doesn't hit you with game errors\n",
    "    if r < 0 or c < 0 or c >= board_size or r >= board_size:\n",
    "        return False\n",
    "    try:\n",
    "        return check_space(r, c)\n",
    "    except:\n",
    "        return None\n",
    "\n",
    "def turn():\n",
    "    dlog('Starting Turn!')\n",
    "    board_size = get_board_size()\n",
    "\n",
    "    team = get_team()\n",
    "    opp_team = Team.WHITE if team == Team.BLACK else team.BLACK\n",
    "    dlog('Team: ' + str(team))\n",
    "\n",
    "    robottype = get_type()\n",
    "    dlog('Type: ' + str(robottype))\n",
    "\n",
    "    if robottype == RobotType.PAWN:\n",
    "        row, col = get_location()\n",
    "        dlog('My location is: ' + str(row) + ' ' + str(col))\n",
    "\n",
    "        if team == Team.WHITE:\n",
    "            forward = 1\n",
    "        else:\n",
    "            forward = -1\n",
    "\n",
    "        # try catpuring pieces\n",
    "        if check_space_wrapper(row + forward, col + 1, board_size) == opp_team: # up and right\n",
    "            capture(row + forward, col + 1)\n",
    "            dlog('Captured at: (' + str(row + forward) + ', ' + str(col + 1) + ')')\n",
    "            # import pdb\n",
    "            # pdb.set_trace()\n",
    "\n",
    "        elif check_space_wrapper(row + forward, col - 1, board_size) == opp_team: # up and left\n",
    "            capture(row + forward, col - 1)\n",
    "            dlog('Captured at: (' + str(row + forward) + ', ' + str(col - 1) + ')')\n",
    "\n",
    "        # otherwise try to move forward\n",
    "        elif row + forward != -1 and row + forward != board_size and not check_space_wrapper(row + forward, col, board_size):\n",
    "            #               ^  not off the board    ^            and    ^ directly forward is empty\n",
    "            move_forward()\n",
    "            dlog('Moved forward!')\n",
    "\n",
    "        # confusion = \"you need a line here to avoid segfault. we aren't sure why but are working on it\"\n",
    "        # ^ I think this is related to the potential ambiguity of what the following else is referring to?\n",
    "\n",
    "    else:\n",
    "        if team == Team.WHITE:\n",
    "            index = 0\n",
    "        else:\n",
    "            index = board_size - 1\n",
    "\n",
    "        for _ in range(board_size):\n",
    "            i = random.randint(0, board_size - 1)\n",
    "            if not check_space(index, i):\n",
    "                spawn(index, i)\n",
    "                dlog('Spawned unit at: (' + str(index) + ', ' + str(i) + ')')\n",
    "                break\n",
    "\n",
    "    bytecode = get_bytecode()\n",
    "    dlog('Done! Bytecode left: ' + str(bytecode))\n",
    "\n",
    "\"\"\""
   ]
  },
  {
   "cell_type": "code",
   "execution_count": 81,
   "metadata": {},
   "outputs": [],
   "source": [
    "examplefuncsturn = \"\"\"\n",
    "dlog('Starting Turn!')\n",
    "board_size = get_board_size()\n",
    "\n",
    "team = get_team()\n",
    "opp_team = Team.WHITE if team == Team.BLACK else team.BLACK\n",
    "dlog('Team: ' + str(team))\n",
    "\n",
    "robottype = get_type()\n",
    "dlog('Type: ' + str(robottype))\n",
    "\n",
    "if robottype == RobotType.PAWN:\n",
    "    row, col = get_location()\n",
    "    dlog('My location is: ' + str(row) + ' ' + str(col))\n",
    "\n",
    "    if team == Team.WHITE:\n",
    "        forward = 1\n",
    "    else:\n",
    "        forward = -1\n",
    "\n",
    "    # try catpuring pieces\n",
    "    if check_space_wrapper(row + forward, col + 1, board_size) == opp_team: # up and right\n",
    "        capture(row + forward, col + 1)\n",
    "        dlog('Captured at: (' + str(row + forward) + ', ' + str(col + 1) + ')')\n",
    "\n",
    "    elif check_space_wrapper(row + forward, col - 1, board_size) == opp_team: # up and left\n",
    "        capture(row + forward, col - 1)\n",
    "        dlog('Captured at: (' + str(row + forward) + ', ' + str(col - 1) + ')')\n",
    "\n",
    "    # otherwise try to move forward\n",
    "    elif row + forward != -1 and row + forward != board_size and not check_space_wrapper(row + forward, col, board_size):\n",
    "        #               ^  not off the board    ^            and    ^ directly forward is empty\n",
    "        move_forward()\n",
    "        dlog('Moved forward!')\n",
    "\n",
    "    # confusion = \"you need a line here to avoid segfault. we aren't sure why but are working on it\"\n",
    "    # ^ I think this is related to the potential ambiguity of what the following else is referring to?\n",
    "\n",
    "else:\n",
    "    if team == Team.WHITE:\n",
    "        index = 0\n",
    "    else:\n",
    "        index = board_size - 1\n",
    "\n",
    "    for _ in range(board_size):\n",
    "        i = random.randint(0, board_size - 1)\n",
    "        if not check_space(index, i):\n",
    "            spawn(index, i)\n",
    "            dlog('Spawned unit at: (' + str(index) + ', ' + str(i) + ')')\n",
    "            break\n",
    "\n",
    "bytecode = get_bytecode()\n",
    "dlog('Done! Bytecode left: ' + str(bytecode))\n",
    "\"\"\""
   ]
  },
  {
   "cell_type": "code",
   "execution_count": 82,
   "metadata": {},
   "outputs": [],
   "source": [
    "\n",
    "class Instruction(SimpleNamespace):\n",
    "    def __init__(self, instruction, in_dict=None):\n",
    "        if in_dict is not None:\n",
    "            super().__init__(**in_dict)\n",
    "        else:\n",
    "            super().__init__(**{a:b for a,b in zip(dis.Instruction._fields+('jump_to', 'was_there', 'extra_extended_args'), instruction + (None, True, 0))})\n",
    "\n",
    "    def is_jumper(self):\n",
    "        return self.is_abs_jumper() or self.is_rel_jumper()\n",
    "\n",
    "    def is_rel_jumper(self):\n",
    "        return self.opcode in dis.hasjrel\n",
    "\n",
    "    def is_abs_jumper(self):\n",
    "        return self.opcode in dis.hasjabs\n",
    "\n",
    "    @classmethod\n",
    "    def ExtendedArgs(self, value):\n",
    "        return Instruction(None, in_dict={\n",
    "            'opcode':144, 'opname':'EXTENDED_ARGS', 'arg':value,\n",
    "            'argval':value, 'argrepr':value, 'offset':None,\n",
    "            'starts_line':None, 'is_jump_target':False, 'was_there': False,\n",
    "            'extra_extended_args': 0,\n",
    "        })\n",
    "\n",
    "    def calculate_offset(self, instructions):\n",
    "        # Return the offset (rel or abs) to self.jump_to in instructions\n",
    "        target_loc = 2 * instructions.index(self.jump_to) - 2 * self.jump_to.extra_extended_args\n",
    "\n",
    "        if self.is_abs_jumper():\n",
    "            return target_loc\n",
    "\n",
    "        self_loc = 2 * instructions.index(self)\n",
    "\n",
    "        return target_loc - self_loc - 2\n"
   ]
  },
  {
   "cell_type": "code",
   "execution_count": 83,
   "metadata": {},
   "outputs": [],
   "source": [
    "def instrument(bytecode):\n",
    "    \"\"\"\n",
    "    The primary method of instrumenting code, which involves injecting a bytecode counter between every instruction to be executed\n",
    "\n",
    "    :param bytecode: a code object, the bytecode submitted by the player\n",
    "    :return: a new code object that has been injected with our bytecode counter\n",
    "    \"\"\"\n",
    "\n",
    "    # Ensure all code constants (e.g. list comprehensions) are also instrumented.\n",
    "    new_consts = []\n",
    "    for i, constant in enumerate(bytecode.co_consts):\n",
    "        if type(constant) == CodeType:\n",
    "            new_consts.append(instrument(constant))\n",
    "        else:\n",
    "            new_consts.append(constant)\n",
    "    new_consts = tuple(new_consts)\n",
    "\n",
    "    instructions = list(dis.get_instructions(bytecode))\n",
    "\n",
    "    function_name_index = len(bytecode.co_names)  # we will be inserting our __instrument__ call at the end of co_names\n",
    "\n",
    "    # the injection, which consists of a function call to an __instrument__ method which increments bytecode\n",
    "    # these three instructions will be inserted between every line of instrumented code\n",
    "    injection = [\n",
    "        dis.Instruction(opcode=116, opname='LOAD_GLOBAL', arg=function_name_index%256, argval='__instrument__', argrepr='__instrument__', offset=None, starts_line=None, is_jump_target=False),\n",
    "        dis.Instruction(opcode=131, opname='CALL_FUNCTION', arg=0, argval=0, argrepr=0, offset=None, starts_line=None, is_jump_target=False),\n",
    "        dis.Instruction(opcode=1, opname='POP_TOP', arg=None, argval=None, argrepr=None, offset=None, starts_line=None, is_jump_target=False)\n",
    "    ]\n",
    "    #extends the opargs so that it can store the index of __instrument__\n",
    "    while function_name_index > 255: #(255 = 2^8 -1 = 1 oparg)\n",
    "        function_name_index >>= 8\n",
    "        injection = [\n",
    "            dis.Instruction(\n",
    "                opcode=144,\n",
    "                opname='EXTENDED_ARGS',\n",
    "                arg=function_name_index%256,\n",
    "                argval=function_name_index%256,\n",
    "                argrepr=function_name_index%256,\n",
    "                offset=None,\n",
    "                starts_line=None,\n",
    "                is_jump_target=False\n",
    "            )\n",
    "        ] + injection\n",
    "\n",
    "    # For maintenance we add an empty jump_to field to each instruction\n",
    "    for i, instruction in enumerate(instructions):\n",
    "        instructions[i] = Instruction(instruction)\n",
    "\n",
    "    # Next, we cache a reference to the jumpers to each jump target in the targets\n",
    "    for i, instruction in enumerate(instructions):\n",
    "        # We're only looking for jumpers\n",
    "        if not instruction.is_jumper():\n",
    "            continue\n",
    "\n",
    "        target = [t for t in instructions if instruction.argval == t.offset][0]\n",
    "        instruction.jump_to = target\n",
    "\n",
    "        # If any targets jump to themselves, that's not kosher.\n",
    "        if instruction == target:\n",
    "            raise SyntaxError('No self-referential loops.')\n",
    "\n",
    "    unsafe = {110, 113, 114, 115, 116, 120, 124, 125, 131, 93, 110, 120, 121, 122, 143, 154, 111, 112, 113, 114, 115, 119}  # bytecode ops that break the instrument\n",
    "\n",
    "    # We then inject the injection before every call, except for those following an EXTENDED_ARGS.\n",
    "    cur_index = -1\n",
    "    for (cur, last) in zip(instructions[:], [None]+instructions[:-1]):\n",
    "        cur_index += 1\n",
    "        if last is not None and last.opcode == 144: #EXTEND_ARG\n",
    "            continue\n",
    "\n",
    "        if last is not None and last.opcode in unsafe:\n",
    "            continue\n",
    "\n",
    "        for j, inject in enumerate(injection):\n",
    "            injected_instruction = Instruction(inject)\n",
    "            injected_instruction.was_there = False # keeping track of the instructions added by us\n",
    "            instructions.insert(cur_index + j, injected_instruction)\n",
    "        cur_index += len(injection)\n",
    "\n",
    "\n",
    "    # Iterate through instructions. If it's a jumper, calculate the new correct offset. For each new offset, if it\n",
    "    # is too large to fit in the current number of EXTENDED_ARGS, inject a new EXTENDED_ARG before it. If you never\n",
    "    # insert a new EXTENDED_ARGS, break out of the loop.\n",
    "    fixed = False\n",
    "    while not fixed:\n",
    "        fixed = True\n",
    "        \n",
    "        print('not fixed!')\n",
    "\n",
    "        i = 0\n",
    "        for instruction in instructions[:]:\n",
    "            instruction.offset = 2 * i\n",
    "\n",
    "            if not instruction.is_jumper():\n",
    "                i += 1\n",
    "                continue\n",
    "\n",
    "            correct_offset = instruction.calculate_offset(instructions)\n",
    "            instruction.arg = correct_offset % 256\n",
    "            correct_offset >>= 8\n",
    "            print('fwt')\n",
    "            extended_args = 0\n",
    "            while correct_offset > 0:\n",
    "                # Check if there is already an EXTENDED_ARGS behind\n",
    "                if i > extended_args and instructions[i - extended_args - 1].opcode == 144:\n",
    "                    instructions[i - extended_args - 1].arg = correct_offset % 256\n",
    "                    print('hheekkkoo')\n",
    "\n",
    "                # Otherwise, insert a new one\n",
    "                else:\n",
    "                    instructions.insert(i, Instruction.ExtendedArgs(correct_offset % 256))\n",
    "                    instruction.extra_extended_args += 1\n",
    "                    print('helo')\n",
    "                    i += 1\n",
    "                    fixed = False\n",
    "\n",
    "                correct_offset >>= 8\n",
    "                extended_args += 1\n",
    "            i += 1\n",
    "    #Maintaining correct line info ( traceback bug fix)\n",
    "    #co_lnotab stores line information in Byte form\n",
    "    # It stores alterantively, the number of instructions to the next increase in line number and\n",
    "    # the increase in line number then\n",
    "    #We need to ensure that these are bytes (You might want to break an increase into two see the article or code below)\n",
    "    #The code did not update these bytes, we need to update the number of instructions before the beginning of each line\n",
    "    #It should be similar to the way the jump to statement were fixed, I tried to mimick them but failed, I feel like I do not inderstand instruction.py\n",
    "    # I am overestimating the number of instructions before the start of the line in this fix\n",
    "    # you might find the end of this article helpful: https://towardsdatascience.com/understanding-python-bytecode-e7edaae8734d\n",
    "    old_lnotab = {} #stores the old right info in a more usefull way (maps instruction num to line num)\n",
    "    i = 0\n",
    "    line_num = 0 #maintains line number by adding differences\n",
    "    instruction_num = 0 #maintains the instruction num by addind differences\n",
    "    while 2*i < len(bytecode.co_lnotab):\n",
    "        instruction_num += bytecode.co_lnotab[2 * i]\n",
    "        line_num += bytecode.co_lnotab[2 * i + 1]\n",
    "        old_lnotab[instruction_num] = line_num\n",
    "        i += 1\n",
    "    #Construct a map from old instruction numbers, to new ones.\n",
    "    num_injected = 0\n",
    "    instruction_index = 0\n",
    "    old_to_new_instruction_num = {}\n",
    "    for instruction in instructions:\n",
    "        if instruction.was_there:\n",
    "            old_to_new_instruction_num[2 * (instruction_index - num_injected)] = 2 * instruction_index\n",
    "        instruction_index += 1\n",
    "        if not instruction.was_there:\n",
    "            num_injected += 1\n",
    "    new_lnotab = {}\n",
    "    for key in old_lnotab:\n",
    "        new_lnotab[old_to_new_instruction_num[key]] = old_lnotab[key]\n",
    "\n",
    "    #Creating a differences list of integers, while ensuring integers in it are bytes\n",
    "    pairs = sorted(new_lnotab.items())\n",
    "    new_lnotab = []\n",
    "    previous_pair = (0, 0)\n",
    "    for pair in pairs:\n",
    "        num_instructions = pair[0] - previous_pair[0]\n",
    "        num_lines = pair[1] - previous_pair[1]\n",
    "        while num_instructions > 127:\n",
    "            new_lnotab.append(127)\n",
    "            new_lnotab.append(0)\n",
    "            num_instructions -= 127\n",
    "        new_lnotab.append(num_instructions)\n",
    "        while num_lines > 127:\n",
    "            new_lnotab.append(127)\n",
    "            new_lnotab.append(0)\n",
    "            num_lines -= 127\n",
    "        new_lnotab.append(num_lines)\n",
    "        previous_pair = pair\n",
    "    #tranfer to bytes and we are good :)\n",
    "    new_lnotab = bytes(new_lnotab)\n",
    "\n",
    "    # Finally, we repackage up our instructions into a byte string and use it to build a new code object\n",
    "    byte_array = [[inst.opcode, 0 if inst.arg is None else inst.arg % 256] for inst in instructions]\n",
    "    new_code = bytes(sum(byte_array, []))\n",
    "\n",
    "    print('wtf')\n",
    "    \n",
    "    # Make sure our code can locate the __instrument__ call\n",
    "    new_names = tuple(bytecode.co_names) + ('__instrument__', )\n",
    "\n",
    "    return Instrument.build_code(bytecode, new_code, new_names, new_consts, new_lnotab)"
   ]
  },
  {
   "cell_type": "code",
   "execution_count": 84,
   "metadata": {},
   "outputs": [],
   "source": [
    "exfuncs = compile_restricted(examplefuncs, 'bot.py', 'exec')"
   ]
  },
  {
   "cell_type": "code",
   "execution_count": 85,
   "metadata": {},
   "outputs": [
    {
     "name": "stdout",
     "output_type": "stream",
     "text": [
      "not fixed!\n",
      "fwt\n",
      "wtf\n",
      "not fixed!\n",
      "fwt\n",
      "fwt\n",
      "fwt\n",
      "fwt\n",
      "fwt\n",
      "wtf\n",
      "not fixed!\n",
      "fwt\n",
      "fwt\n",
      "fwt\n",
      "hheekkkoo\n",
      "fwt\n",
      "helo\n",
      "fwt\n",
      "fwt\n",
      "hheekkkoo\n",
      "fwt\n",
      "helo\n",
      "fwt\n",
      "hheekkkoo\n",
      "fwt\n",
      "fwt\n",
      "hheekkkoo\n",
      "fwt\n",
      "hheekkkoo\n",
      "fwt\n",
      "hheekkkoo\n",
      "fwt\n",
      "helo\n",
      "fwt\n",
      "hheekkkoo\n",
      "fwt\n",
      "fwt\n",
      "fwt\n",
      "fwt\n",
      "hheekkkoo\n",
      "fwt\n",
      "hheekkkoo\n",
      "not fixed!\n",
      "fwt\n",
      "fwt\n",
      "fwt\n",
      "hheekkkoo\n",
      "fwt\n",
      "hheekkkoo\n",
      "fwt\n",
      "fwt\n",
      "hheekkkoo\n",
      "fwt\n",
      "hheekkkoo\n",
      "fwt\n",
      "hheekkkoo\n",
      "fwt\n",
      "fwt\n",
      "hheekkkoo\n",
      "fwt\n",
      "hheekkkoo\n",
      "fwt\n",
      "hheekkkoo\n",
      "fwt\n",
      "hheekkkoo\n",
      "fwt\n",
      "hheekkkoo\n",
      "fwt\n",
      "fwt\n",
      "fwt\n",
      "fwt\n",
      "hheekkkoo\n",
      "fwt\n",
      "hheekkkoo\n",
      "wtf\n",
      "not fixed!\n",
      "wtf\n"
     ]
    }
   ],
   "source": [
    "exfuncs = instrument(exfuncs)"
   ]
  },
  {
   "cell_type": "code",
   "execution_count": 86,
   "metadata": {},
   "outputs": [],
   "source": [
    "code = {'bot': exfuncs}"
   ]
  },
  {
   "cell_type": "code",
   "execution_count": 87,
   "metadata": {},
   "outputs": [
    {
     "name": "stdout",
     "output_type": "stream",
     "text": [
      "\u001b[32m[Game info] Seed: 1337\u001b[0m\n"
     ]
    }
   ],
   "source": [
    "game = Game([code,code],debug=True)"
   ]
  },
  {
   "cell_type": "code",
   "execution_count": 99,
   "metadata": {},
   "outputs": [
    {
     "name": "stdout",
     "output_type": "stream",
     "text": [
      "\u001b[32m[Game info] Turn 12\u001b[0m\n",
      "\u001b[32m[Game info] Queue: {6: <ROBOT 6 WHITE>, 7: <ROBOT 7 BLACK>, 8: <ROBOT 8 BLACK>, 9: <ROBOT 9 WHITE>, 10: <ROBOT 10 WHITE>, 11: <ROBOT 11 BLACK>, 12: <ROBOT 12 BLACK>, 13: <ROBOT 13 WHITE>, 14: <ROBOT 14 WHITE>, 15: <ROBOT 15 BLACK>, 16: <ROBOT 16 BLACK>, 17: <ROBOT 17 WHITE>, 18: <ROBOT 18 WHITE>, 19: <ROBOT 19 BLACK>, 20: <ROBOT 20 BLACK>, 21: <ROBOT 21 WHITE>, 22: <ROBOT 22 WHITE>, 23: <ROBOT 23 BLACK>}\u001b[0m\n",
      "\u001b[32m[Game info] Lords: [<ROBOT BLACK HQ BLACK>, <ROBOT WHITE HQ WHITE>]\u001b[0m\n",
      "[Robot 6 WHITE log] Starting Turn!\n",
      "[Robot 6 WHITE log] Team: Team.WHITE\n",
      "[Robot 6 WHITE log] Type: RobotType.PAWN\n",
      "[Robot 6 WHITE log] My location is: 8 12\n",
      "[Robot 6 WHITE log] Done! Bytecode left: 19917\n",
      "[Robot 7 BLACK log] Starting Turn!\n",
      "[Robot 7 BLACK log] Team: Team.BLACK\n",
      "[Robot 7 BLACK log] Type: RobotType.PAWN\n",
      "[Robot 7 BLACK log] My location is: 7 9\n",
      "[Robot 7 BLACK log] Moved forward!\n",
      "[Robot 7 BLACK log] Done! Bytecode left: 19909\n",
      "[Robot 8 BLACK log] Starting Turn!\n",
      "[Robot 8 BLACK log] Team: Team.BLACK\n",
      "[Robot 8 BLACK log] Type: RobotType.PAWN\n",
      "[Robot 8 BLACK log] My location is: 9 12\n",
      "[Robot 8 BLACK log] Done! Bytecode left: 19917\n",
      "[Robot 9 WHITE log] Starting Turn!\n",
      "[Robot 9 WHITE log] Team: Team.WHITE\n",
      "[Robot 9 WHITE log] Type: RobotType.PAWN\n",
      "[Robot 9 WHITE log] My location is: 7 5\n",
      "[Robot 9 WHITE log] Moved forward!\n",
      "[Robot 9 WHITE log] Done! Bytecode left: 19909\n",
      "[Robot 10 WHITE log] Starting Turn!\n",
      "[Robot 10 WHITE log] Team: Team.WHITE\n",
      "[Robot 10 WHITE log] Type: RobotType.PAWN\n",
      "[Robot 10 WHITE log] My location is: 6 11\n",
      "[Robot 10 WHITE log] Moved forward!\n",
      "[Robot 10 WHITE log] Done! Bytecode left: 19909\n",
      "[Robot 11 BLACK log] Starting Turn!\n",
      "[Robot 11 BLACK log] Team: Team.BLACK\n",
      "[Robot 11 BLACK log] Type: RobotType.PAWN\n",
      "[Robot 11 BLACK log] My location is: 9 3\n",
      "[Robot 11 BLACK log] Moved forward!\n",
      "[Robot 11 BLACK log] Done! Bytecode left: 19909\n",
      "[Robot 12 BLACK log] Starting Turn!\n",
      "[Robot 12 BLACK log] Team: Team.BLACK\n",
      "[Robot 12 BLACK log] Type: RobotType.PAWN\n",
      "[Robot 12 BLACK log] My location is: 10 13\n",
      "[Robot 12 BLACK log] Moved forward!\n",
      "[Robot 12 BLACK log] Done! Bytecode left: 19909\n",
      "[Robot 13 WHITE log] Starting Turn!\n",
      "[Robot 13 WHITE log] Team: Team.WHITE\n",
      "[Robot 13 WHITE log] Type: RobotType.PAWN\n",
      "[Robot 13 WHITE log] My location is: 5 12\n",
      "[Robot 13 WHITE log] Moved forward!\n",
      "[Robot 13 WHITE log] Done! Bytecode left: 19909\n",
      "[Robot 14 WHITE log] Starting Turn!\n",
      "[Robot 14 WHITE log] Team: Team.WHITE\n",
      "[Robot 14 WHITE log] Type: RobotType.PAWN\n",
      "[Robot 14 WHITE log] My location is: 4 2\n",
      "[Robot 14 WHITE log] Moved forward!\n",
      "[Robot 14 WHITE log] Done! Bytecode left: 19909\n",
      "[Robot 15 BLACK log] Starting Turn!\n",
      "[Robot 15 BLACK log] Team: Team.BLACK\n",
      "[Robot 15 BLACK log] Type: RobotType.PAWN\n",
      "[Robot 15 BLACK log] My location is: 11 11\n",
      "[Robot 15 BLACK log] Moved forward!\n",
      "[Robot 15 BLACK log] Done! Bytecode left: 19909\n",
      "[Robot 16 BLACK log] Starting Turn!\n",
      "[Robot 16 BLACK log] Team: Team.BLACK\n",
      "[Robot 16 BLACK log] Type: RobotType.PAWN\n",
      "[Robot 16 BLACK log] My location is: 12 12\n",
      "[Robot 16 BLACK log] Moved forward!\n",
      "[Robot 16 BLACK log] Done! Bytecode left: 19909\n",
      "[Robot 17 WHITE log] Starting Turn!\n",
      "[Robot 17 WHITE log] Team: Team.WHITE\n",
      "[Robot 17 WHITE log] Type: RobotType.PAWN\n",
      "[Robot 17 WHITE log] My location is: 3 12\n",
      "[Robot 17 WHITE log] Moved forward!\n",
      "[Robot 17 WHITE log] Done! Bytecode left: 19909\n",
      "[Robot 18 WHITE log] Starting Turn!\n",
      "[Robot 18 WHITE log] Team: Team.WHITE\n",
      "[Robot 18 WHITE log] Type: RobotType.PAWN\n",
      "[Robot 18 WHITE log] My location is: 2 9\n",
      "[Robot 18 WHITE log] Moved forward!\n",
      "[Robot 18 WHITE log] Done! Bytecode left: 19909\n",
      "[Robot 19 BLACK log] Starting Turn!\n",
      "[Robot 19 BLACK log] Team: Team.BLACK\n",
      "[Robot 19 BLACK log] Type: RobotType.PAWN\n",
      "[Robot 19 BLACK log] My location is: 13 0\n",
      "[Robot 19 BLACK log] Moved forward!\n",
      "[Robot 19 BLACK log] Done! Bytecode left: 19910\n",
      "[Robot 20 BLACK log] Starting Turn!\n",
      "[Robot 20 BLACK log] Team: Team.BLACK\n",
      "[Robot 20 BLACK log] Type: RobotType.PAWN\n",
      "[Robot 20 BLACK log] My location is: 14 11\n",
      "[Robot 20 BLACK log] Moved forward!\n",
      "[Robot 20 BLACK log] Done! Bytecode left: 19909\n",
      "[Robot 21 WHITE log] Starting Turn!\n",
      "[Robot 21 WHITE log] Team: Team.WHITE\n",
      "[Robot 21 WHITE log] Type: RobotType.PAWN\n",
      "[Robot 21 WHITE log] My location is: 1 3\n",
      "[Robot 21 WHITE log] Moved forward!\n",
      "[Robot 21 WHITE log] Done! Bytecode left: 19909\n",
      "[Robot 22 WHITE log] Starting Turn!\n",
      "[Robot 22 WHITE log] Team: Team.WHITE\n",
      "[Robot 22 WHITE log] Type: RobotType.PAWN\n",
      "[Robot 22 WHITE log] My location is: 0 14\n",
      "[Robot 22 WHITE log] Moved forward!\n",
      "[Robot 22 WHITE log] Done! Bytecode left: 19889\n",
      "[Robot 23 BLACK log] Starting Turn!\n",
      "[Robot 23 BLACK log] Team: Team.BLACK\n",
      "[Robot 23 BLACK log] Type: RobotType.PAWN\n",
      "[Robot 23 BLACK log] My location is: 15 7\n",
      "[Robot 23 BLACK log] Moved forward!\n",
      "[Robot 23 BLACK log] Done! Bytecode left: 19889\n",
      "[Robot BLACK HQ log] Starting Turn!\n",
      "[Robot BLACK HQ log] Team: Team.BLACK\n",
      "[Robot BLACK HQ log] Type: RobotType.OVERLORD\n",
      "[Robot BLACK HQ log] Spawned unit at: (15, 5)\n",
      "[Robot BLACK HQ log] Done! Bytecode left: 19948\n",
      "[Robot WHITE HQ log] Starting Turn!\n",
      "[Robot WHITE HQ log] Team: Team.WHITE\n",
      "[Robot WHITE HQ log] Type: RobotType.OVERLORD\n",
      "[Robot WHITE HQ log] Spawned unit at: (0, 10)\n",
      "[Robot WHITE HQ log] Done! Bytecode left: 19949\n"
     ]
    }
   ],
   "source": [
    "game.turn()"
   ]
  },
  {
   "cell_type": "code",
   "execution_count": 3,
   "metadata": {},
   "outputs": [
    {
     "data": {
      "text/plain": [
       "[93, 110, 120, 121, 122, 143, 154]"
      ]
     },
     "execution_count": 3,
     "metadata": {},
     "output_type": "execute_result"
    }
   ],
   "source": [
    "dis.hasjrel"
   ]
  },
  {
   "cell_type": "code",
   "execution_count": 6,
   "metadata": {},
   "outputs": [
    {
     "data": {
      "text/plain": [
       "[111, 112, 113, 114, 115, 119]"
      ]
     },
     "execution_count": 6,
     "metadata": {},
     "output_type": "execute_result"
    }
   ],
   "source": [
    "dis.hasjabs"
   ]
  },
  {
   "cell_type": "code",
   "execution_count": 5,
   "metadata": {},
   "outputs": [],
   "source": [
    "s = \"\"\"\n",
    "if x == 1:\n",
    "    if y == 1:\n",
    "        print(x)\n",
    "    else:\n",
    "        print(y)\n",
    "    x = 1\n",
    "else:\n",
    "    print(2)\n",
    "\"\"\""
   ]
  },
  {
   "cell_type": "code",
   "execution_count": 9,
   "metadata": {},
   "outputs": [],
   "source": [
    "s2 = \"\"\"\n",
    "if x == 1:\n",
    "    if y == 1:\n",
    "        print(x)\n",
    "    elif x == 1:\n",
    "        print(z)\n",
    "    else:\n",
    "        print(y)\n",
    "else:\n",
    "    print(2)\n",
    "\"\"\""
   ]
  },
  {
   "cell_type": "code",
   "execution_count": 10,
   "metadata": {},
   "outputs": [
    {
     "name": "stdout",
     "output_type": "stream",
     "text": [
      "  2           0 LOAD_NAME                0 (x)\n",
      "              2 LOAD_CONST               0 (1)\n",
      "              4 COMPARE_OP               2 (==)\n",
      "              6 POP_JUMP_IF_FALSE       40\n",
      "\n",
      "  3           8 LOAD_NAME                1 (y)\n",
      "             10 LOAD_CONST               0 (1)\n",
      "             12 COMPARE_OP               2 (==)\n",
      "             14 POP_JUMP_IF_FALSE       26\n",
      "\n",
      "  4          16 LOAD_NAME                2 (print)\n",
      "             18 LOAD_NAME                0 (x)\n",
      "             20 CALL_FUNCTION            1\n",
      "             22 POP_TOP\n",
      "             24 JUMP_FORWARD             8 (to 34)\n",
      "\n",
      "  6     >>   26 LOAD_NAME                2 (print)\n",
      "             28 LOAD_NAME                1 (y)\n",
      "             30 CALL_FUNCTION            1\n",
      "             32 POP_TOP\n",
      "\n",
      "  7     >>   34 LOAD_CONST               0 (1)\n",
      "             36 STORE_NAME               0 (x)\n",
      "             38 JUMP_FORWARD             8 (to 48)\n",
      "\n",
      "  9     >>   40 LOAD_NAME                2 (print)\n",
      "             42 LOAD_CONST               1 (2)\n",
      "             44 CALL_FUNCTION            1\n",
      "             46 POP_TOP\n",
      "        >>   48 LOAD_CONST               2 (None)\n",
      "             50 RETURN_VALUE\n"
     ]
    }
   ],
   "source": [
    "dis.dis(s)"
   ]
  },
  {
   "cell_type": "code",
   "execution_count": 11,
   "metadata": {},
   "outputs": [
    {
     "name": "stdout",
     "output_type": "stream",
     "text": [
      "  2           0 LOAD_NAME                0 (x)\n",
      "              2 LOAD_CONST               0 (1)\n",
      "              4 COMPARE_OP               2 (==)\n",
      "              6 POP_JUMP_IF_FALSE       54\n",
      "\n",
      "  3           8 LOAD_NAME                1 (y)\n",
      "             10 LOAD_CONST               0 (1)\n",
      "             12 COMPARE_OP               2 (==)\n",
      "             14 POP_JUMP_IF_FALSE       26\n",
      "\n",
      "  4          16 LOAD_NAME                2 (print)\n",
      "             18 LOAD_NAME                0 (x)\n",
      "             20 CALL_FUNCTION            1\n",
      "             22 POP_TOP\n",
      "             24 JUMP_ABSOLUTE           62\n",
      "\n",
      "  5     >>   26 LOAD_NAME                0 (x)\n",
      "             28 LOAD_CONST               0 (1)\n",
      "             30 COMPARE_OP               2 (==)\n",
      "             32 POP_JUMP_IF_FALSE       44\n",
      "\n",
      "  6          34 LOAD_NAME                2 (print)\n",
      "             36 LOAD_NAME                3 (z)\n",
      "             38 CALL_FUNCTION            1\n",
      "             40 POP_TOP\n",
      "             42 JUMP_ABSOLUTE           62\n",
      "\n",
      "  8     >>   44 LOAD_NAME                2 (print)\n",
      "             46 LOAD_NAME                1 (y)\n",
      "             48 CALL_FUNCTION            1\n",
      "             50 POP_TOP\n",
      "             52 JUMP_FORWARD             8 (to 62)\n",
      "\n",
      " 10     >>   54 LOAD_NAME                2 (print)\n",
      "             56 LOAD_CONST               1 (2)\n",
      "             58 CALL_FUNCTION            1\n",
      "             60 POP_TOP\n",
      "        >>   62 LOAD_CONST               2 (None)\n",
      "             64 RETURN_VALUE\n"
     ]
    }
   ],
   "source": [
    "dis.dis(s2)"
   ]
  },
  {
   "cell_type": "code",
   "execution_count": 75,
   "metadata": {},
   "outputs": [
    {
     "name": "stdout",
     "output_type": "stream",
     "text": [
      "  2           0 LOAD_GLOBAL             30 (__instrument__)\n",
      "              2 CALL_FUNCTION            0\n",
      "              4 POP_TOP\n",
      "              6 LOAD_NAME                0 (dlog)\n",
      "              8 LOAD_GLOBAL             30 (__instrument__)\n",
      "             10 CALL_FUNCTION            0\n",
      "             12 POP_TOP\n",
      "             14 LOAD_CONST               0 ('Starting Turn!')\n",
      "             16 LOAD_GLOBAL             30 (__instrument__)\n",
      "             18 CALL_FUNCTION            0\n",
      "             20 POP_TOP\n",
      "             22 CALL_FUNCTION            1\n",
      "             24 POP_TOP\n",
      "             26 LOAD_GLOBAL             30 (__instrument__)\n",
      "             28 CALL_FUNCTION            0\n",
      "             30 POP_TOP\n",
      "\n",
      "  3          32 LOAD_NAME                1 (get_board_size)\n",
      "             34 LOAD_GLOBAL             30 (__instrument__)\n",
      "             36 CALL_FUNCTION            0\n",
      "             38 POP_TOP\n",
      "             40 CALL_FUNCTION            0\n",
      "             42 STORE_NAME               2 (board_size)\n",
      "             44 LOAD_GLOBAL             30 (__instrument__)\n",
      "             46 CALL_FUNCTION            0\n",
      "             48 POP_TOP\n",
      "\n",
      "  5          50 LOAD_NAME                3 (get_team)\n",
      "             52 LOAD_GLOBAL             30 (__instrument__)\n",
      "             54 CALL_FUNCTION            0\n",
      "             56 POP_TOP\n",
      "             58 CALL_FUNCTION            0\n",
      "             60 STORE_NAME               4 (team)\n",
      "             62 LOAD_GLOBAL             30 (__instrument__)\n",
      "             64 CALL_FUNCTION            0\n",
      "             66 POP_TOP\n",
      "\n",
      "  6          68 LOAD_NAME                4 (team)\n",
      "             70 LOAD_GLOBAL             30 (__instrument__)\n",
      "             72 CALL_FUNCTION            0\n",
      "             74 POP_TOP\n",
      "             76 LOAD_NAME                5 (_getattr_)\n",
      "             78 LOAD_GLOBAL             30 (__instrument__)\n",
      "             80 CALL_FUNCTION            0\n",
      "             82 POP_TOP\n",
      "             84 LOAD_NAME                6 (Team)\n",
      "             86 LOAD_GLOBAL             30 (__instrument__)\n",
      "             88 CALL_FUNCTION            0\n",
      "             90 POP_TOP\n",
      "             92 LOAD_CONST               1 ('BLACK')\n",
      "             94 LOAD_GLOBAL             30 (__instrument__)\n",
      "             96 CALL_FUNCTION            0\n",
      "             98 POP_TOP\n",
      "            100 CALL_FUNCTION            2\n",
      "            102 COMPARE_OP               2 (==)\n",
      "            104 LOAD_GLOBAL             30 (__instrument__)\n",
      "            106 CALL_FUNCTION            0\n",
      "            108 POP_TOP\n",
      "            110 POP_JUMP_IF_FALSE      140\n",
      "            112 LOAD_NAME                5 (_getattr_)\n",
      "            114 LOAD_GLOBAL             30 (__instrument__)\n",
      "            116 CALL_FUNCTION            0\n",
      "            118 POP_TOP\n",
      "            120 LOAD_NAME                6 (Team)\n",
      "            122 LOAD_GLOBAL             30 (__instrument__)\n",
      "            124 CALL_FUNCTION            0\n",
      "            126 POP_TOP\n",
      "            128 LOAD_CONST               2 ('WHITE')\n",
      "            130 LOAD_GLOBAL             30 (__instrument__)\n",
      "            132 CALL_FUNCTION            0\n",
      "            134 POP_TOP\n",
      "            136 CALL_FUNCTION            2\n",
      "            138 JUMP_FORWARD            26 (to 166)\n",
      "        >>  140 LOAD_NAME                5 (_getattr_)\n",
      "            142 LOAD_GLOBAL             30 (__instrument__)\n",
      "            144 CALL_FUNCTION            0\n",
      "            146 POP_TOP\n",
      "            148 LOAD_NAME                4 (team)\n",
      "            150 LOAD_GLOBAL             30 (__instrument__)\n",
      "            152 CALL_FUNCTION            0\n",
      "            154 POP_TOP\n",
      "            156 LOAD_CONST               1 ('BLACK')\n",
      "            158 LOAD_GLOBAL             30 (__instrument__)\n",
      "            160 CALL_FUNCTION            0\n",
      "            162 POP_TOP\n",
      "            164 CALL_FUNCTION            2\n",
      "        >>  166 STORE_NAME               7 (opp_team)\n",
      "            168 LOAD_GLOBAL             30 (__instrument__)\n",
      "            170 CALL_FUNCTION            0\n",
      "            172 POP_TOP\n",
      "\n",
      "  7         174 LOAD_NAME                0 (dlog)\n",
      "            176 LOAD_GLOBAL             30 (__instrument__)\n",
      "            178 CALL_FUNCTION            0\n",
      "            180 POP_TOP\n",
      "            182 LOAD_CONST               3 ('Team: ')\n",
      "            184 LOAD_GLOBAL             30 (__instrument__)\n",
      "            186 CALL_FUNCTION            0\n",
      "            188 POP_TOP\n",
      "            190 LOAD_NAME                8 (str)\n",
      "            192 LOAD_GLOBAL             30 (__instrument__)\n",
      "            194 CALL_FUNCTION            0\n",
      "            196 POP_TOP\n",
      "            198 LOAD_NAME                4 (team)\n",
      "            200 LOAD_GLOBAL             30 (__instrument__)\n",
      "            202 CALL_FUNCTION            0\n",
      "            204 POP_TOP\n",
      "            206 CALL_FUNCTION            1\n",
      "            208 BINARY_ADD\n",
      "            210 LOAD_GLOBAL             30 (__instrument__)\n",
      "            212 CALL_FUNCTION            0\n",
      "            214 POP_TOP\n",
      "            216 CALL_FUNCTION            1\n",
      "            218 POP_TOP\n",
      "            220 LOAD_GLOBAL             30 (__instrument__)\n",
      "            222 CALL_FUNCTION            0\n",
      "            224 POP_TOP\n",
      "\n",
      "  9         226 LOAD_NAME                9 (get_type)\n",
      "            228 LOAD_GLOBAL             30 (__instrument__)\n",
      "            230 CALL_FUNCTION            0\n",
      "            232 POP_TOP\n",
      "            234 CALL_FUNCTION            0\n",
      "            236 STORE_NAME              10 (robottype)\n",
      "            238 LOAD_GLOBAL             30 (__instrument__)\n",
      "            240 CALL_FUNCTION            0\n",
      "            242 POP_TOP\n",
      "\n",
      " 10         244 LOAD_NAME                0 (dlog)\n",
      "            246 LOAD_GLOBAL             30 (__instrument__)\n",
      "            248 CALL_FUNCTION            0\n",
      "            250 POP_TOP\n",
      "            252 LOAD_CONST               4 ('Type: ')\n",
      "            254 LOAD_GLOBAL             30 (__instrument__)\n",
      "            256 CALL_FUNCTION            0\n",
      "            258 POP_TOP\n",
      "            260 LOAD_NAME                8 (str)\n",
      "            262 LOAD_GLOBAL             30 (__instrument__)\n",
      "            264 CALL_FUNCTION            0\n",
      "            266 POP_TOP\n",
      "            268 LOAD_NAME               10 (robottype)\n",
      "            270 LOAD_GLOBAL             30 (__instrument__)\n",
      "            272 CALL_FUNCTION            0\n",
      "            274 POP_TOP\n",
      "            276 CALL_FUNCTION            1\n",
      "            278 BINARY_ADD\n",
      "            280 LOAD_GLOBAL             30 (__instrument__)\n",
      "            282 CALL_FUNCTION            0\n",
      "            284 POP_TOP\n",
      "            286 CALL_FUNCTION            1\n",
      "            288 POP_TOP\n",
      "            290 LOAD_GLOBAL             30 (__instrument__)\n",
      "            292 CALL_FUNCTION            0\n",
      "            294 POP_TOP\n",
      "\n",
      " 12         296 LOAD_NAME               10 (robottype)\n",
      "            298 LOAD_GLOBAL             30 (__instrument__)\n",
      "            300 CALL_FUNCTION            0\n",
      "            302 POP_TOP\n",
      "            304 LOAD_NAME                5 (_getattr_)\n",
      "            306 LOAD_GLOBAL             30 (__instrument__)\n",
      "            308 CALL_FUNCTION            0\n",
      "            310 POP_TOP\n",
      "            312 LOAD_NAME               11 (RobotType)\n",
      "            314 LOAD_GLOBAL             30 (__instrument__)\n",
      "            316 CALL_FUNCTION            0\n",
      "            318 POP_TOP\n",
      "            320 LOAD_CONST               5 ('PAWN')\n",
      "            322 LOAD_GLOBAL             30 (__instrument__)\n",
      "            324 CALL_FUNCTION            0\n",
      "            326 POP_TOP\n",
      "            328 CALL_FUNCTION            2\n",
      "            330 COMPARE_OP               2 (==)\n",
      "            332 LOAD_GLOBAL             30 (__instrument__)\n",
      "            334 CALL_FUNCTION            0\n",
      "            336 POP_TOP\n",
      "            338 EXTENDED_ARG             5\n",
      "            340 POP_JUMP_IF_FALSE     1384\n",
      "\n",
      " 13         342 LOAD_NAME               12 (_unpack_sequence_)\n",
      "            344 LOAD_GLOBAL             30 (__instrument__)\n",
      "            346 CALL_FUNCTION            0\n",
      "            348 POP_TOP\n",
      "            350 LOAD_NAME               13 (get_location)\n",
      "            352 LOAD_GLOBAL             30 (__instrument__)\n",
      "            354 CALL_FUNCTION            0\n",
      "            356 POP_TOP\n",
      "            358 CALL_FUNCTION            0\n",
      "            360 LOAD_CONST               6 (())\n",
      "            362 LOAD_GLOBAL             30 (__instrument__)\n",
      "            364 CALL_FUNCTION            0\n",
      "            366 POP_TOP\n",
      "            368 LOAD_CONST               7 (2)\n",
      "            370 LOAD_GLOBAL             30 (__instrument__)\n",
      "            372 CALL_FUNCTION            0\n",
      "            374 POP_TOP\n",
      "            376 LOAD_CONST               8 (('childs', 'min_len'))\n",
      "            378 LOAD_GLOBAL             30 (__instrument__)\n",
      "            380 CALL_FUNCTION            0\n",
      "            382 POP_TOP\n",
      "            384 BUILD_CONST_KEY_MAP      2\n",
      "            386 LOAD_GLOBAL             30 (__instrument__)\n",
      "            388 CALL_FUNCTION            0\n",
      "            390 POP_TOP\n",
      "            392 LOAD_NAME               14 (_getiter_)\n",
      "            394 LOAD_GLOBAL             30 (__instrument__)\n",
      "            396 CALL_FUNCTION            0\n",
      "            398 POP_TOP\n",
      "            400 CALL_FUNCTION            3\n",
      "            402 UNPACK_SEQUENCE          2\n",
      "            404 LOAD_GLOBAL             30 (__instrument__)\n",
      "            406 CALL_FUNCTION            0\n",
      "            408 POP_TOP\n",
      "            410 STORE_NAME              15 (row)\n",
      "            412 LOAD_GLOBAL             30 (__instrument__)\n",
      "            414 CALL_FUNCTION            0\n",
      "            416 POP_TOP\n",
      "            418 STORE_NAME              16 (col)\n",
      "            420 LOAD_GLOBAL             30 (__instrument__)\n",
      "            422 CALL_FUNCTION            0\n",
      "            424 POP_TOP\n",
      "\n",
      " 14         426 LOAD_NAME                0 (dlog)\n",
      "            428 LOAD_GLOBAL             30 (__instrument__)\n",
      "            430 CALL_FUNCTION            0\n",
      "            432 POP_TOP\n",
      "            434 LOAD_CONST               9 ('My location is: ')\n",
      "            436 LOAD_GLOBAL             30 (__instrument__)\n",
      "            438 CALL_FUNCTION            0\n",
      "            440 POP_TOP\n",
      "            442 LOAD_NAME                8 (str)\n",
      "            444 LOAD_GLOBAL             30 (__instrument__)\n",
      "            446 CALL_FUNCTION            0\n",
      "            448 POP_TOP\n",
      "            450 LOAD_NAME               15 (row)\n",
      "            452 LOAD_GLOBAL             30 (__instrument__)\n",
      "            454 CALL_FUNCTION            0\n",
      "            456 POP_TOP\n",
      "            458 CALL_FUNCTION            1\n",
      "            460 BINARY_ADD\n",
      "            462 LOAD_GLOBAL             30 (__instrument__)\n",
      "            464 CALL_FUNCTION            0\n",
      "            466 POP_TOP\n",
      "            468 LOAD_CONST              10 (' ')\n",
      "            470 LOAD_GLOBAL             30 (__instrument__)\n",
      "            472 CALL_FUNCTION            0\n",
      "            474 POP_TOP\n",
      "            476 BINARY_ADD\n",
      "            478 LOAD_GLOBAL             30 (__instrument__)\n",
      "            480 CALL_FUNCTION            0\n",
      "            482 POP_TOP\n",
      "            484 LOAD_NAME                8 (str)\n",
      "            486 LOAD_GLOBAL             30 (__instrument__)\n",
      "            488 CALL_FUNCTION            0\n",
      "            490 POP_TOP\n",
      "            492 LOAD_NAME               16 (col)\n",
      "            494 LOAD_GLOBAL             30 (__instrument__)\n",
      "            496 CALL_FUNCTION            0\n",
      "            498 POP_TOP\n",
      "            500 CALL_FUNCTION            1\n",
      "            502 BINARY_ADD\n",
      "            504 LOAD_GLOBAL             30 (__instrument__)\n",
      "            506 CALL_FUNCTION            0\n",
      "            508 POP_TOP\n",
      "            510 CALL_FUNCTION            1\n",
      "            512 POP_TOP\n",
      "            514 LOAD_GLOBAL             30 (__instrument__)\n",
      "            516 CALL_FUNCTION            0\n",
      "            518 POP_TOP\n",
      "\n",
      " 16         520 LOAD_NAME                4 (team)\n",
      "            522 LOAD_GLOBAL             30 (__instrument__)\n",
      "            524 CALL_FUNCTION            0\n",
      "            526 POP_TOP\n",
      "            528 LOAD_NAME                5 (_getattr_)\n",
      "            530 LOAD_GLOBAL             30 (__instrument__)\n",
      "            532 CALL_FUNCTION            0\n",
      "            534 POP_TOP\n",
      "            536 LOAD_NAME                6 (Team)\n",
      "            538 LOAD_GLOBAL             30 (__instrument__)\n",
      "            540 CALL_FUNCTION            0\n",
      "            542 POP_TOP\n",
      "            544 LOAD_CONST               2 ('WHITE')\n",
      "            546 LOAD_GLOBAL             30 (__instrument__)\n",
      "            548 CALL_FUNCTION            0\n",
      "            550 POP_TOP\n",
      "            552 CALL_FUNCTION            2\n",
      "            554 COMPARE_OP               2 (==)\n",
      "            556 LOAD_GLOBAL             30 (__instrument__)\n",
      "            558 CALL_FUNCTION            0\n",
      "            560 POP_TOP\n",
      "            562 EXTENDED_ARG             2\n",
      "            564 POP_JUMP_IF_FALSE      584\n",
      "\n",
      " 17         566 LOAD_CONST              11 (1)\n",
      "            568 LOAD_GLOBAL             30 (__instrument__)\n",
      "            570 CALL_FUNCTION            0\n",
      "            572 POP_TOP\n",
      "            574 STORE_NAME              17 (forward)\n",
      "            576 LOAD_GLOBAL             30 (__instrument__)\n",
      "            578 CALL_FUNCTION            0\n",
      "            580 POP_TOP\n",
      "            582 JUMP_FORWARD            16 (to 600)\n",
      "\n",
      " 19     >>  584 LOAD_CONST              12 (-1)\n",
      "            586 LOAD_GLOBAL             30 (__instrument__)\n",
      "            588 CALL_FUNCTION            0\n",
      "            590 POP_TOP\n",
      "            592 STORE_NAME              17 (forward)\n",
      "            594 LOAD_GLOBAL             30 (__instrument__)\n",
      "            596 CALL_FUNCTION            0\n",
      "            598 POP_TOP\n",
      "\n",
      " 22     >>  600 LOAD_NAME               18 (check_space_wrapper)\n",
      "            602 LOAD_GLOBAL             30 (__instrument__)\n",
      "            604 CALL_FUNCTION            0\n",
      "            606 POP_TOP\n",
      "            608 LOAD_NAME               15 (row)\n",
      "            610 LOAD_GLOBAL             30 (__instrument__)\n",
      "            612 CALL_FUNCTION            0\n",
      "            614 POP_TOP\n",
      "            616 LOAD_NAME               17 (forward)\n",
      "            618 LOAD_GLOBAL             30 (__instrument__)\n",
      "            620 CALL_FUNCTION            0\n",
      "            622 POP_TOP\n",
      "            624 BINARY_ADD\n",
      "            626 LOAD_GLOBAL             30 (__instrument__)\n",
      "            628 CALL_FUNCTION            0\n",
      "            630 POP_TOP\n",
      "            632 LOAD_NAME               16 (col)\n",
      "            634 LOAD_GLOBAL             30 (__instrument__)\n",
      "            636 CALL_FUNCTION            0\n",
      "            638 POP_TOP\n",
      "            640 LOAD_CONST              11 (1)\n",
      "            642 LOAD_GLOBAL             30 (__instrument__)\n",
      "            644 CALL_FUNCTION            0\n",
      "            646 POP_TOP\n",
      "            648 BINARY_ADD\n",
      "            650 LOAD_GLOBAL             30 (__instrument__)\n",
      "            652 CALL_FUNCTION            0\n",
      "            654 POP_TOP\n",
      "            656 LOAD_NAME                2 (board_size)\n",
      "            658 LOAD_GLOBAL             30 (__instrument__)\n",
      "            660 CALL_FUNCTION            0\n",
      "            662 POP_TOP\n",
      "            664 CALL_FUNCTION            3\n",
      "            666 LOAD_NAME                7 (opp_team)\n",
      "            668 LOAD_GLOBAL             30 (__instrument__)\n",
      "            670 CALL_FUNCTION            0\n",
      "            672 POP_TOP\n",
      "            674 COMPARE_OP               2 (==)\n",
      "            676 LOAD_GLOBAL             30 (__instrument__)\n",
      "            678 CALL_FUNCTION            0\n",
      "            680 POP_TOP\n",
      "            682 EXTENDED_ARG             3\n",
      "            684 POP_JUMP_IF_FALSE      898\n",
      "\n",
      " 23         686 LOAD_NAME               19 (capture)\n",
      "            688 LOAD_GLOBAL             30 (__instrument__)\n",
      "            690 CALL_FUNCTION            0\n",
      "            692 POP_TOP\n",
      "            694 LOAD_NAME               15 (row)\n",
      "            696 LOAD_GLOBAL             30 (__instrument__)\n",
      "            698 CALL_FUNCTION            0\n",
      "            700 POP_TOP\n",
      "            702 LOAD_NAME               17 (forward)\n",
      "            704 LOAD_GLOBAL             30 (__instrument__)\n",
      "            706 CALL_FUNCTION            0\n",
      "            708 POP_TOP\n",
      "            710 BINARY_ADD\n",
      "            712 LOAD_GLOBAL             30 (__instrument__)\n",
      "            714 CALL_FUNCTION            0\n",
      "            716 POP_TOP\n",
      "            718 LOAD_NAME               16 (col)\n",
      "            720 LOAD_GLOBAL             30 (__instrument__)\n",
      "            722 CALL_FUNCTION            0\n",
      "            724 POP_TOP\n",
      "            726 LOAD_CONST              11 (1)\n",
      "            728 LOAD_GLOBAL             30 (__instrument__)\n",
      "            730 CALL_FUNCTION            0\n",
      "            732 POP_TOP\n",
      "            734 BINARY_ADD\n",
      "            736 LOAD_GLOBAL             30 (__instrument__)\n",
      "            738 CALL_FUNCTION            0\n",
      "            740 POP_TOP\n",
      "            742 CALL_FUNCTION            2\n",
      "            744 POP_TOP\n",
      "            746 LOAD_GLOBAL             30 (__instrument__)\n",
      "            748 CALL_FUNCTION            0\n",
      "            750 POP_TOP\n",
      "\n",
      " 24         752 LOAD_NAME                0 (dlog)\n",
      "            754 LOAD_GLOBAL             30 (__instrument__)\n",
      "            756 CALL_FUNCTION            0\n",
      "            758 POP_TOP\n",
      "            760 LOAD_CONST              13 ('Captured at: (')\n",
      "            762 LOAD_GLOBAL             30 (__instrument__)\n",
      "            764 CALL_FUNCTION            0\n",
      "            766 POP_TOP\n",
      "            768 LOAD_NAME                8 (str)\n",
      "            770 LOAD_GLOBAL             30 (__instrument__)\n",
      "            772 CALL_FUNCTION            0\n",
      "            774 POP_TOP\n",
      "            776 LOAD_NAME               15 (row)\n",
      "            778 LOAD_GLOBAL             30 (__instrument__)\n",
      "            780 CALL_FUNCTION            0\n",
      "            782 POP_TOP\n",
      "            784 LOAD_NAME               17 (forward)\n",
      "            786 LOAD_GLOBAL             30 (__instrument__)\n",
      "            788 CALL_FUNCTION            0\n",
      "            790 POP_TOP\n",
      "            792 BINARY_ADD\n",
      "            794 LOAD_GLOBAL             30 (__instrument__)\n",
      "            796 CALL_FUNCTION            0\n",
      "            798 POP_TOP\n",
      "            800 CALL_FUNCTION            1\n",
      "            802 BINARY_ADD\n",
      "            804 LOAD_GLOBAL             30 (__instrument__)\n",
      "            806 CALL_FUNCTION            0\n",
      "            808 POP_TOP\n",
      "            810 LOAD_CONST              14 (', ')\n",
      "            812 LOAD_GLOBAL             30 (__instrument__)\n",
      "            814 CALL_FUNCTION            0\n",
      "            816 POP_TOP\n",
      "            818 BINARY_ADD\n",
      "            820 LOAD_GLOBAL             30 (__instrument__)\n",
      "            822 CALL_FUNCTION            0\n",
      "            824 POP_TOP\n",
      "            826 LOAD_NAME                8 (str)\n",
      "            828 LOAD_GLOBAL             30 (__instrument__)\n",
      "            830 CALL_FUNCTION            0\n",
      "            832 POP_TOP\n",
      "            834 LOAD_NAME               16 (col)\n",
      "            836 LOAD_GLOBAL             30 (__instrument__)\n",
      "            838 CALL_FUNCTION            0\n",
      "            840 POP_TOP\n",
      "            842 LOAD_CONST              11 (1)\n",
      "            844 LOAD_GLOBAL             30 (__instrument__)\n",
      "            846 CALL_FUNCTION            0\n",
      "            848 POP_TOP\n",
      "            850 BINARY_ADD\n",
      "            852 LOAD_GLOBAL             30 (__instrument__)\n",
      "            854 CALL_FUNCTION            0\n",
      "            856 POP_TOP\n",
      "            858 CALL_FUNCTION            1\n",
      "            860 BINARY_ADD\n",
      "            862 LOAD_GLOBAL             30 (__instrument__)\n",
      "            864 CALL_FUNCTION            0\n",
      "            866 POP_TOP\n",
      "            868 LOAD_CONST              15 (')')\n",
      "            870 LOAD_GLOBAL             30 (__instrument__)\n",
      "            872 CALL_FUNCTION            0\n",
      "            874 POP_TOP\n",
      "            876 BINARY_ADD\n",
      "            878 LOAD_GLOBAL             30 (__instrument__)\n",
      "            880 CALL_FUNCTION            0\n",
      "            882 POP_TOP\n",
      "            884 CALL_FUNCTION            1\n",
      "            886 POP_TOP\n",
      "            888 LOAD_GLOBAL             30 (__instrument__)\n",
      "            890 CALL_FUNCTION            0\n",
      "            892 POP_TOP\n",
      "            894 EXTENDED_ARG             1\n",
      "            896 JUMP_FORWARD           482 (to 1380)\n",
      "\n",
      " 26     >>  898 LOAD_NAME               18 (check_space_wrapper)\n",
      "            900 LOAD_GLOBAL             30 (__instrument__)\n",
      "            902 CALL_FUNCTION            0\n",
      "            904 POP_TOP\n",
      "            906 LOAD_NAME               15 (row)\n",
      "            908 LOAD_GLOBAL             30 (__instrument__)\n",
      "            910 CALL_FUNCTION            0\n",
      "            912 POP_TOP\n",
      "            914 LOAD_NAME               17 (forward)\n",
      "            916 LOAD_GLOBAL             30 (__instrument__)\n",
      "            918 CALL_FUNCTION            0\n",
      "            920 POP_TOP\n",
      "            922 BINARY_ADD\n",
      "            924 LOAD_GLOBAL             30 (__instrument__)\n",
      "            926 CALL_FUNCTION            0\n",
      "            928 POP_TOP\n",
      "            930 LOAD_NAME               16 (col)\n",
      "            932 LOAD_GLOBAL             30 (__instrument__)\n",
      "            934 CALL_FUNCTION            0\n",
      "            936 POP_TOP\n",
      "            938 LOAD_CONST              11 (1)\n",
      "            940 LOAD_GLOBAL             30 (__instrument__)\n",
      "            942 CALL_FUNCTION            0\n",
      "            944 POP_TOP\n",
      "            946 BINARY_SUBTRACT\n",
      "            948 LOAD_GLOBAL             30 (__instrument__)\n",
      "            950 CALL_FUNCTION            0\n",
      "            952 POP_TOP\n",
      "            954 LOAD_NAME                2 (board_size)\n",
      "            956 LOAD_GLOBAL             30 (__instrument__)\n",
      "            958 CALL_FUNCTION            0\n",
      "            960 POP_TOP\n",
      "            962 CALL_FUNCTION            3\n",
      "            964 LOAD_NAME                7 (opp_team)\n",
      "            966 LOAD_GLOBAL             30 (__instrument__)\n",
      "            968 CALL_FUNCTION            0\n",
      "            970 POP_TOP\n",
      "            972 COMPARE_OP               2 (==)\n",
      "            974 LOAD_GLOBAL             30 (__instrument__)\n",
      "            976 CALL_FUNCTION            0\n",
      "            978 POP_TOP\n",
      "            980 EXTENDED_ARG             4\n",
      "            982 POP_JUMP_IF_FALSE     1194\n",
      "\n",
      " 27         984 LOAD_NAME               19 (capture)\n",
      "            986 LOAD_GLOBAL             30 (__instrument__)\n",
      "            988 CALL_FUNCTION            0\n",
      "            990 POP_TOP\n",
      "            992 LOAD_NAME               15 (row)\n",
      "            994 LOAD_GLOBAL             30 (__instrument__)\n",
      "            996 CALL_FUNCTION            0\n",
      "            998 POP_TOP\n",
      "           1000 LOAD_NAME               17 (forward)\n",
      "           1002 LOAD_GLOBAL             30 (__instrument__)\n",
      "           1004 CALL_FUNCTION            0\n",
      "           1006 POP_TOP\n",
      "           1008 BINARY_ADD\n",
      "           1010 LOAD_GLOBAL             30 (__instrument__)\n",
      "           1012 CALL_FUNCTION            0\n",
      "           1014 POP_TOP\n",
      "           1016 LOAD_NAME               16 (col)\n",
      "           1018 LOAD_GLOBAL             30 (__instrument__)\n",
      "           1020 CALL_FUNCTION            0\n",
      "           1022 POP_TOP\n",
      "           1024 LOAD_CONST              11 (1)\n",
      "           1026 LOAD_GLOBAL             30 (__instrument__)\n",
      "           1028 CALL_FUNCTION            0\n",
      "           1030 POP_TOP\n",
      "           1032 BINARY_SUBTRACT\n",
      "           1034 LOAD_GLOBAL             30 (__instrument__)\n",
      "           1036 CALL_FUNCTION            0\n",
      "           1038 POP_TOP\n",
      "           1040 CALL_FUNCTION            2\n",
      "           1042 POP_TOP\n",
      "           1044 LOAD_GLOBAL             30 (__instrument__)\n",
      "           1046 CALL_FUNCTION            0\n",
      "           1048 POP_TOP\n",
      "\n",
      " 28        1050 LOAD_NAME                0 (dlog)\n",
      "           1052 LOAD_GLOBAL             30 (__instrument__)\n",
      "           1054 CALL_FUNCTION            0\n",
      "           1056 POP_TOP\n",
      "           1058 LOAD_CONST              13 ('Captured at: (')\n",
      "           1060 LOAD_GLOBAL             30 (__instrument__)\n",
      "           1062 CALL_FUNCTION            0\n",
      "           1064 POP_TOP\n",
      "           1066 LOAD_NAME                8 (str)\n",
      "           1068 LOAD_GLOBAL             30 (__instrument__)\n",
      "           1070 CALL_FUNCTION            0\n",
      "           1072 POP_TOP\n",
      "           1074 LOAD_NAME               15 (row)\n",
      "           1076 LOAD_GLOBAL             30 (__instrument__)\n",
      "           1078 CALL_FUNCTION            0\n",
      "           1080 POP_TOP\n",
      "           1082 LOAD_NAME               17 (forward)\n",
      "           1084 LOAD_GLOBAL             30 (__instrument__)\n",
      "           1086 CALL_FUNCTION            0\n",
      "           1088 POP_TOP\n",
      "           1090 BINARY_ADD\n",
      "           1092 LOAD_GLOBAL             30 (__instrument__)\n",
      "           1094 CALL_FUNCTION            0\n",
      "           1096 POP_TOP\n",
      "           1098 CALL_FUNCTION            1\n",
      "           1100 BINARY_ADD\n",
      "           1102 LOAD_GLOBAL             30 (__instrument__)\n",
      "           1104 CALL_FUNCTION            0\n",
      "           1106 POP_TOP\n",
      "           1108 LOAD_CONST              14 (', ')\n",
      "           1110 LOAD_GLOBAL             30 (__instrument__)\n",
      "           1112 CALL_FUNCTION            0\n",
      "           1114 POP_TOP\n",
      "           1116 BINARY_ADD\n",
      "           1118 LOAD_GLOBAL             30 (__instrument__)\n",
      "           1120 CALL_FUNCTION            0\n",
      "           1122 POP_TOP\n",
      "           1124 LOAD_NAME                8 (str)\n",
      "           1126 LOAD_GLOBAL             30 (__instrument__)\n",
      "           1128 CALL_FUNCTION            0\n",
      "           1130 POP_TOP\n",
      "           1132 LOAD_NAME               16 (col)\n",
      "           1134 LOAD_GLOBAL             30 (__instrument__)\n",
      "           1136 CALL_FUNCTION            0\n",
      "           1138 POP_TOP\n",
      "           1140 LOAD_CONST              11 (1)\n",
      "           1142 LOAD_GLOBAL             30 (__instrument__)\n",
      "           1144 CALL_FUNCTION            0\n",
      "           1146 POP_TOP\n",
      "           1148 BINARY_SUBTRACT\n",
      "           1150 LOAD_GLOBAL             30 (__instrument__)\n",
      "           1152 CALL_FUNCTION            0\n",
      "           1154 POP_TOP\n",
      "           1156 CALL_FUNCTION            1\n",
      "           1158 BINARY_ADD\n",
      "           1160 LOAD_GLOBAL             30 (__instrument__)\n",
      "           1162 CALL_FUNCTION            0\n",
      "           1164 POP_TOP\n",
      "           1166 LOAD_CONST              15 (')')\n",
      "           1168 LOAD_GLOBAL             30 (__instrument__)\n",
      "           1170 CALL_FUNCTION            0\n",
      "           1172 POP_TOP\n",
      "           1174 BINARY_ADD\n",
      "           1176 LOAD_GLOBAL             30 (__instrument__)\n",
      "           1178 CALL_FUNCTION            0\n",
      "           1180 POP_TOP\n",
      "           1182 CALL_FUNCTION            1\n",
      "           1184 POP_TOP\n",
      "           1186 LOAD_GLOBAL             30 (__instrument__)\n",
      "           1188 CALL_FUNCTION            0\n",
      "           1190 POP_TOP\n",
      "           1192 JUMP_FORWARD           186 (to 1380)\n",
      "\n",
      " 31     >> 1194 LOAD_NAME               15 (row)\n",
      "           1196 LOAD_GLOBAL             30 (__instrument__)\n",
      "           1198 CALL_FUNCTION            0\n",
      "           1200 POP_TOP\n",
      "           1202 LOAD_NAME               17 (forward)\n",
      "           1204 LOAD_GLOBAL             30 (__instrument__)\n",
      "           1206 CALL_FUNCTION            0\n",
      "           1208 POP_TOP\n",
      "           1210 BINARY_ADD\n",
      "           1212 LOAD_GLOBAL             30 (__instrument__)\n",
      "           1214 CALL_FUNCTION            0\n",
      "           1216 POP_TOP\n",
      "           1218 LOAD_CONST              12 (-1)\n",
      "           1220 LOAD_GLOBAL             30 (__instrument__)\n",
      "           1222 CALL_FUNCTION            0\n",
      "           1224 POP_TOP\n",
      "           1226 COMPARE_OP               3 (!=)\n",
      "           1228 LOAD_GLOBAL             30 (__instrument__)\n",
      "           1230 CALL_FUNCTION            0\n",
      "           1232 POP_TOP\n",
      "           1234 EXTENDED_ARG             7\n",
      "           1236 POP_JUMP_IF_FALSE     1794\n",
      "           1238 LOAD_NAME               15 (row)\n",
      "           1240 LOAD_GLOBAL             30 (__instrument__)\n",
      "           1242 CALL_FUNCTION            0\n",
      "           1244 POP_TOP\n",
      "           1246 LOAD_NAME               17 (forward)\n",
      "           1248 LOAD_GLOBAL             30 (__instrument__)\n",
      "           1250 CALL_FUNCTION            0\n",
      "           1252 POP_TOP\n",
      "           1254 BINARY_ADD\n",
      "           1256 LOAD_GLOBAL             30 (__instrument__)\n",
      "           1258 CALL_FUNCTION            0\n",
      "           1260 POP_TOP\n",
      "           1262 LOAD_NAME                2 (board_size)\n",
      "           1264 LOAD_GLOBAL             30 (__instrument__)\n",
      "           1266 CALL_FUNCTION            0\n",
      "           1268 POP_TOP\n",
      "           1270 COMPARE_OP               3 (!=)\n",
      "           1272 LOAD_GLOBAL             30 (__instrument__)\n",
      "           1274 CALL_FUNCTION            0\n",
      "           1276 POP_TOP\n",
      "           1278 EXTENDED_ARG             7\n",
      "           1280 POP_JUMP_IF_FALSE     1794\n",
      "           1282 LOAD_NAME               18 (check_space_wrapper)\n",
      "           1284 LOAD_GLOBAL             30 (__instrument__)\n",
      "           1286 CALL_FUNCTION            0\n",
      "           1288 POP_TOP\n",
      "           1290 LOAD_NAME               15 (row)\n",
      "           1292 LOAD_GLOBAL             30 (__instrument__)\n",
      "           1294 CALL_FUNCTION            0\n",
      "           1296 POP_TOP\n",
      "           1298 LOAD_NAME               17 (forward)\n",
      "           1300 LOAD_GLOBAL             30 (__instrument__)\n",
      "           1302 CALL_FUNCTION            0\n",
      "           1304 POP_TOP\n",
      "           1306 BINARY_ADD\n",
      "           1308 LOAD_GLOBAL             30 (__instrument__)\n",
      "           1310 CALL_FUNCTION            0\n",
      "           1312 POP_TOP\n",
      "           1314 LOAD_NAME               16 (col)\n",
      "           1316 LOAD_GLOBAL             30 (__instrument__)\n",
      "           1318 CALL_FUNCTION            0\n",
      "           1320 POP_TOP\n",
      "           1322 LOAD_NAME                2 (board_size)\n",
      "           1324 LOAD_GLOBAL             30 (__instrument__)\n",
      "           1326 CALL_FUNCTION            0\n",
      "           1328 POP_TOP\n",
      "           1330 CALL_FUNCTION            3\n",
      "           1332 EXTENDED_ARG             7\n",
      "           1334 POP_JUMP_IF_TRUE      1794\n",
      "\n",
      " 33        1336 LOAD_NAME               20 (move_forward)\n",
      "           1338 LOAD_GLOBAL             30 (__instrument__)\n",
      "           1340 CALL_FUNCTION            0\n",
      "           1342 POP_TOP\n",
      "           1344 CALL_FUNCTION            0\n",
      "           1346 POP_TOP\n",
      "           1348 LOAD_GLOBAL             30 (__instrument__)\n",
      "           1350 CALL_FUNCTION            0\n",
      "           1352 POP_TOP\n",
      "\n",
      " 34        1354 LOAD_NAME                0 (dlog)\n",
      "           1356 LOAD_GLOBAL             30 (__instrument__)\n",
      "           1358 CALL_FUNCTION            0\n",
      "           1360 POP_TOP\n",
      "           1362 LOAD_CONST              16 ('Moved forward!')\n",
      "           1364 LOAD_GLOBAL             30 (__instrument__)\n",
      "           1366 CALL_FUNCTION            0\n",
      "           1368 POP_TOP\n",
      "           1370 CALL_FUNCTION            1\n",
      "           1372 POP_TOP\n",
      "           1374 LOAD_GLOBAL             30 (__instrument__)\n",
      "           1376 CALL_FUNCTION            0\n",
      "           1378 POP_TOP\n",
      "        >> 1380 EXTENDED_ARG             1\n",
      "           1382 JUMP_FORWARD           410 (to 1794)\n",
      "\n",
      " 40     >> 1384 LOAD_NAME                4 (team)\n",
      "           1386 LOAD_GLOBAL             30 (__instrument__)\n",
      "           1388 CALL_FUNCTION            0\n",
      "           1390 POP_TOP\n",
      "           1392 LOAD_NAME                5 (_getattr_)\n",
      "           1394 LOAD_GLOBAL             30 (__instrument__)\n",
      "           1396 CALL_FUNCTION            0\n",
      "           1398 POP_TOP\n",
      "           1400 LOAD_NAME                6 (Team)\n",
      "           1402 LOAD_GLOBAL             30 (__instrument__)\n",
      "           1404 CALL_FUNCTION            0\n",
      "           1406 POP_TOP\n",
      "           1408 LOAD_CONST               2 ('WHITE')\n",
      "           1410 LOAD_GLOBAL             30 (__instrument__)\n",
      "           1412 CALL_FUNCTION            0\n",
      "           1414 POP_TOP\n",
      "           1416 CALL_FUNCTION            2\n",
      "           1418 COMPARE_OP               2 (==)\n",
      "           1420 LOAD_GLOBAL             30 (__instrument__)\n",
      "           1422 CALL_FUNCTION            0\n",
      "           1424 POP_TOP\n",
      "           1426 EXTENDED_ARG             5\n",
      "           1428 POP_JUMP_IF_FALSE     1448\n",
      "\n",
      " 41        1430 LOAD_CONST              17 (0)\n",
      "           1432 LOAD_GLOBAL             30 (__instrument__)\n",
      "           1434 CALL_FUNCTION            0\n",
      "           1436 POP_TOP\n",
      "           1438 STORE_NAME              21 (index)\n",
      "           1440 LOAD_GLOBAL             30 (__instrument__)\n",
      "           1442 CALL_FUNCTION            0\n",
      "           1444 POP_TOP\n",
      "           1446 JUMP_FORWARD            32 (to 1480)\n",
      "\n",
      " 43     >> 1448 LOAD_NAME                2 (board_size)\n",
      "           1450 LOAD_GLOBAL             30 (__instrument__)\n",
      "           1452 CALL_FUNCTION            0\n",
      "           1454 POP_TOP\n",
      "           1456 LOAD_CONST              11 (1)\n",
      "           1458 LOAD_GLOBAL             30 (__instrument__)\n",
      "           1460 CALL_FUNCTION            0\n",
      "           1462 POP_TOP\n",
      "           1464 BINARY_SUBTRACT\n",
      "           1466 LOAD_GLOBAL             30 (__instrument__)\n",
      "           1468 CALL_FUNCTION            0\n",
      "           1470 POP_TOP\n",
      "           1472 STORE_NAME              21 (index)\n",
      "           1474 LOAD_GLOBAL             30 (__instrument__)\n",
      "           1476 CALL_FUNCTION            0\n",
      "           1478 POP_TOP\n",
      "        >> 1480 EXTENDED_ARG             1\n",
      "\n",
      " 45        1482 SETUP_LOOP             310 (to 1794)\n",
      "           1484 LOAD_NAME               14 (_getiter_)\n",
      "           1486 LOAD_GLOBAL             30 (__instrument__)\n",
      "           1488 CALL_FUNCTION            0\n",
      "           1490 POP_TOP\n",
      "           1492 LOAD_NAME               22 (range)\n",
      "           1494 LOAD_GLOBAL             30 (__instrument__)\n",
      "           1496 CALL_FUNCTION            0\n",
      "           1498 POP_TOP\n",
      "           1500 LOAD_NAME                2 (board_size)\n",
      "           1502 LOAD_GLOBAL             30 (__instrument__)\n",
      "           1504 CALL_FUNCTION            0\n",
      "           1506 POP_TOP\n",
      "           1508 CALL_FUNCTION            1\n",
      "           1510 CALL_FUNCTION            1\n",
      "           1512 GET_ITER\n",
      "           1514 LOAD_GLOBAL             30 (__instrument__)\n",
      "           1516 CALL_FUNCTION            0\n",
      "           1518 POP_TOP\n",
      "        >> 1520 EXTENDED_ARG             1\n",
      "           1522 FOR_ITER               262 (to 1786)\n",
      "           1524 STORE_NAME              23 (_)\n",
      "           1526 LOAD_GLOBAL             30 (__instrument__)\n",
      "           1528 CALL_FUNCTION            0\n",
      "           1530 POP_TOP\n",
      "\n",
      " 46        1532 LOAD_NAME                5 (_getattr_)\n",
      "           1534 LOAD_GLOBAL             30 (__instrument__)\n",
      "           1536 CALL_FUNCTION            0\n",
      "           1538 POP_TOP\n",
      "           1540 LOAD_NAME               24 (random)\n",
      "           1542 LOAD_GLOBAL             30 (__instrument__)\n",
      "           1544 CALL_FUNCTION            0\n",
      "           1546 POP_TOP\n",
      "           1548 LOAD_CONST              18 ('randint')\n",
      "           1550 LOAD_GLOBAL             30 (__instrument__)\n",
      "           1552 CALL_FUNCTION            0\n",
      "           1554 POP_TOP\n",
      "           1556 CALL_FUNCTION            2\n",
      "           1558 LOAD_CONST              17 (0)\n",
      "           1560 LOAD_GLOBAL             30 (__instrument__)\n",
      "           1562 CALL_FUNCTION            0\n",
      "           1564 POP_TOP\n",
      "           1566 LOAD_NAME                2 (board_size)\n",
      "           1568 LOAD_GLOBAL             30 (__instrument__)\n",
      "           1570 CALL_FUNCTION            0\n",
      "           1572 POP_TOP\n",
      "           1574 LOAD_CONST              11 (1)\n",
      "           1576 LOAD_GLOBAL             30 (__instrument__)\n",
      "           1578 CALL_FUNCTION            0\n",
      "           1580 POP_TOP\n",
      "           1582 BINARY_SUBTRACT\n",
      "           1584 LOAD_GLOBAL             30 (__instrument__)\n",
      "           1586 CALL_FUNCTION            0\n",
      "           1588 POP_TOP\n",
      "           1590 CALL_FUNCTION            2\n",
      "           1592 STORE_NAME              25 (i)\n",
      "           1594 LOAD_GLOBAL             30 (__instrument__)\n",
      "           1596 CALL_FUNCTION            0\n",
      "           1598 POP_TOP\n",
      "\n",
      " 47        1600 LOAD_NAME               26 (check_space)\n",
      "           1602 LOAD_GLOBAL             30 (__instrument__)\n",
      "           1604 CALL_FUNCTION            0\n",
      "           1606 POP_TOP\n",
      "           1608 LOAD_NAME               21 (index)\n",
      "           1610 LOAD_GLOBAL             30 (__instrument__)\n",
      "           1612 CALL_FUNCTION            0\n",
      "           1614 POP_TOP\n",
      "           1616 LOAD_NAME               25 (i)\n",
      "           1618 LOAD_GLOBAL             30 (__instrument__)\n",
      "           1620 CALL_FUNCTION            0\n",
      "           1622 POP_TOP\n",
      "           1624 CALL_FUNCTION            2\n",
      "           1626 EXTENDED_ARG             5\n",
      "           1628 POP_JUMP_IF_TRUE      1520\n",
      "\n",
      " 48        1630 LOAD_NAME               27 (spawn)\n",
      "           1632 LOAD_GLOBAL             30 (__instrument__)\n",
      "           1634 CALL_FUNCTION            0\n",
      "           1636 POP_TOP\n",
      "           1638 LOAD_NAME               21 (index)\n",
      "           1640 LOAD_GLOBAL             30 (__instrument__)\n",
      "           1642 CALL_FUNCTION            0\n",
      "           1644 POP_TOP\n",
      "           1646 LOAD_NAME               25 (i)\n",
      "           1648 LOAD_GLOBAL             30 (__instrument__)\n",
      "           1650 CALL_FUNCTION            0\n",
      "           1652 POP_TOP\n",
      "           1654 CALL_FUNCTION            2\n",
      "           1656 POP_TOP\n",
      "           1658 LOAD_GLOBAL             30 (__instrument__)\n",
      "           1660 CALL_FUNCTION            0\n",
      "           1662 POP_TOP\n",
      "\n",
      " 49        1664 LOAD_NAME                0 (dlog)\n",
      "           1666 LOAD_GLOBAL             30 (__instrument__)\n",
      "           1668 CALL_FUNCTION            0\n",
      "           1670 POP_TOP\n",
      "           1672 LOAD_CONST              19 ('Spawned unit at: (')\n",
      "           1674 LOAD_GLOBAL             30 (__instrument__)\n",
      "           1676 CALL_FUNCTION            0\n",
      "           1678 POP_TOP\n",
      "           1680 LOAD_NAME                8 (str)\n",
      "           1682 LOAD_GLOBAL             30 (__instrument__)\n",
      "           1684 CALL_FUNCTION            0\n",
      "           1686 POP_TOP\n",
      "           1688 LOAD_NAME               21 (index)\n",
      "           1690 LOAD_GLOBAL             30 (__instrument__)\n",
      "           1692 CALL_FUNCTION            0\n",
      "           1694 POP_TOP\n",
      "           1696 CALL_FUNCTION            1\n",
      "           1698 BINARY_ADD\n",
      "           1700 LOAD_GLOBAL             30 (__instrument__)\n",
      "           1702 CALL_FUNCTION            0\n",
      "           1704 POP_TOP\n",
      "           1706 LOAD_CONST              14 (', ')\n",
      "           1708 LOAD_GLOBAL             30 (__instrument__)\n",
      "           1710 CALL_FUNCTION            0\n",
      "           1712 POP_TOP\n",
      "           1714 BINARY_ADD\n",
      "           1716 LOAD_GLOBAL             30 (__instrument__)\n",
      "           1718 CALL_FUNCTION            0\n",
      "           1720 POP_TOP\n",
      "           1722 LOAD_NAME                8 (str)\n",
      "           1724 LOAD_GLOBAL             30 (__instrument__)\n",
      "           1726 CALL_FUNCTION            0\n",
      "           1728 POP_TOP\n",
      "           1730 LOAD_NAME               25 (i)\n",
      "           1732 LOAD_GLOBAL             30 (__instrument__)\n",
      "           1734 CALL_FUNCTION            0\n",
      "           1736 POP_TOP\n",
      "           1738 CALL_FUNCTION            1\n",
      "           1740 BINARY_ADD\n",
      "           1742 LOAD_GLOBAL             30 (__instrument__)\n",
      "           1744 CALL_FUNCTION            0\n",
      "           1746 POP_TOP\n",
      "           1748 LOAD_CONST              15 (')')\n",
      "           1750 LOAD_GLOBAL             30 (__instrument__)\n",
      "           1752 CALL_FUNCTION            0\n",
      "           1754 POP_TOP\n",
      "           1756 BINARY_ADD\n",
      "           1758 LOAD_GLOBAL             30 (__instrument__)\n",
      "           1760 CALL_FUNCTION            0\n",
      "           1762 POP_TOP\n",
      "           1764 CALL_FUNCTION            1\n",
      "           1766 POP_TOP\n",
      "           1768 LOAD_GLOBAL             30 (__instrument__)\n",
      "           1770 CALL_FUNCTION            0\n",
      "           1772 POP_TOP\n",
      "\n",
      " 50        1774 BREAK_LOOP\n",
      "           1776 LOAD_GLOBAL             30 (__instrument__)\n",
      "           1778 CALL_FUNCTION            0\n",
      "           1780 POP_TOP\n",
      "           1782 EXTENDED_ARG             5\n",
      "           1784 JUMP_ABSOLUTE         1520\n",
      "        >> 1786 POP_BLOCK\n",
      "           1788 LOAD_GLOBAL             30 (__instrument__)\n",
      "           1790 CALL_FUNCTION            0\n",
      "           1792 POP_TOP\n",
      "\n",
      " 52     >> 1794 LOAD_NAME               28 (get_bytecode)\n",
      "           1796 LOAD_GLOBAL             30 (__instrument__)\n",
      "           1798 CALL_FUNCTION            0\n",
      "           1800 POP_TOP\n",
      "           1802 CALL_FUNCTION            0\n",
      "           1804 STORE_NAME              29 (bytecode)\n",
      "           1806 LOAD_GLOBAL             30 (__instrument__)\n",
      "           1808 CALL_FUNCTION            0\n",
      "           1810 POP_TOP\n",
      "\n",
      " 53        1812 LOAD_NAME                0 (dlog)\n",
      "           1814 LOAD_GLOBAL             30 (__instrument__)\n",
      "           1816 CALL_FUNCTION            0\n",
      "           1818 POP_TOP\n",
      "           1820 LOAD_CONST              20 ('Done! Bytecode left: ')\n",
      "           1822 LOAD_GLOBAL             30 (__instrument__)\n",
      "           1824 CALL_FUNCTION            0\n",
      "           1826 POP_TOP\n",
      "           1828 LOAD_NAME                8 (str)\n",
      "           1830 LOAD_GLOBAL             30 (__instrument__)\n",
      "           1832 CALL_FUNCTION            0\n",
      "           1834 POP_TOP\n",
      "           1836 LOAD_NAME               29 (bytecode)\n",
      "           1838 LOAD_GLOBAL             30 (__instrument__)\n",
      "           1840 CALL_FUNCTION            0\n",
      "           1842 POP_TOP\n",
      "           1844 CALL_FUNCTION            1\n",
      "           1846 BINARY_ADD\n",
      "           1848 LOAD_GLOBAL             30 (__instrument__)\n",
      "           1850 CALL_FUNCTION            0\n",
      "           1852 POP_TOP\n",
      "           1854 CALL_FUNCTION            1\n",
      "           1856 POP_TOP\n",
      "           1858 LOAD_GLOBAL             30 (__instrument__)\n",
      "           1860 CALL_FUNCTION            0\n",
      "           1862 POP_TOP\n",
      "           1864 LOAD_CONST              21 (None)\n",
      "           1866 LOAD_GLOBAL             30 (__instrument__)\n",
      "           1868 CALL_FUNCTION            0\n",
      "           1870 POP_TOP\n",
      "           1872 RETURN_VALUE\n"
     ]
    }
   ],
   "source": [
    "dis.dis(exfuncs)"
   ]
  },
  {
   "cell_type": "code",
   "execution_count": 76,
   "metadata": {},
   "outputs": [
    {
     "name": "stdout",
     "output_type": "stream",
     "text": [
      "  2           0 LOAD_NAME                0 (dlog)\n",
      "              2 LOAD_CONST               0 ('Starting Turn!')\n",
      "              4 CALL_FUNCTION            1\n",
      "              6 POP_TOP\n",
      "\n",
      "  3           8 LOAD_NAME                1 (get_board_size)\n",
      "             10 CALL_FUNCTION            0\n",
      "             12 STORE_NAME               2 (board_size)\n",
      "\n",
      "  5          14 LOAD_NAME                3 (get_team)\n",
      "             16 CALL_FUNCTION            0\n",
      "             18 STORE_NAME               4 (team)\n",
      "\n",
      "  6          20 LOAD_NAME                4 (team)\n",
      "             22 LOAD_NAME                5 (Team)\n",
      "             24 LOAD_ATTR                6 (BLACK)\n",
      "             26 COMPARE_OP               2 (==)\n",
      "             28 POP_JUMP_IF_FALSE       36\n",
      "             30 LOAD_NAME                5 (Team)\n",
      "             32 LOAD_ATTR                7 (WHITE)\n",
      "             34 JUMP_FORWARD             4 (to 40)\n",
      "        >>   36 LOAD_NAME                4 (team)\n",
      "             38 LOAD_ATTR                6 (BLACK)\n",
      "        >>   40 STORE_NAME               8 (opp_team)\n",
      "\n",
      "  7          42 LOAD_NAME                0 (dlog)\n",
      "             44 LOAD_CONST               1 ('Team: ')\n",
      "             46 LOAD_NAME                9 (str)\n",
      "             48 LOAD_NAME                4 (team)\n",
      "             50 CALL_FUNCTION            1\n",
      "             52 BINARY_ADD\n",
      "             54 CALL_FUNCTION            1\n",
      "             56 POP_TOP\n",
      "\n",
      "  9          58 LOAD_NAME               10 (get_type)\n",
      "             60 CALL_FUNCTION            0\n",
      "             62 STORE_NAME              11 (robottype)\n",
      "\n",
      " 10          64 LOAD_NAME                0 (dlog)\n",
      "             66 LOAD_CONST               2 ('Type: ')\n",
      "             68 LOAD_NAME                9 (str)\n",
      "             70 LOAD_NAME               11 (robottype)\n",
      "             72 CALL_FUNCTION            1\n",
      "             74 BINARY_ADD\n",
      "             76 CALL_FUNCTION            1\n",
      "             78 POP_TOP\n",
      "\n",
      " 12          80 LOAD_NAME               11 (robottype)\n",
      "             82 LOAD_NAME               12 (RobotType)\n",
      "             84 LOAD_ATTR               13 (PAWN)\n",
      "             86 COMPARE_OP               2 (==)\n",
      "             88 EXTENDED_ARG             1\n",
      "             90 POP_JUMP_IF_FALSE      382\n",
      "\n",
      " 13          92 LOAD_NAME               14 (get_location)\n",
      "             94 CALL_FUNCTION            0\n",
      "             96 UNPACK_SEQUENCE          2\n",
      "             98 STORE_NAME              15 (row)\n",
      "            100 STORE_NAME              16 (col)\n",
      "\n",
      " 14         102 LOAD_NAME                0 (dlog)\n",
      "            104 LOAD_CONST               3 ('My location is: ')\n",
      "            106 LOAD_NAME                9 (str)\n",
      "            108 LOAD_NAME               15 (row)\n",
      "            110 CALL_FUNCTION            1\n",
      "            112 BINARY_ADD\n",
      "            114 LOAD_CONST               4 (' ')\n",
      "            116 BINARY_ADD\n",
      "            118 LOAD_NAME                9 (str)\n",
      "            120 LOAD_NAME               16 (col)\n",
      "            122 CALL_FUNCTION            1\n",
      "            124 BINARY_ADD\n",
      "            126 CALL_FUNCTION            1\n",
      "            128 POP_TOP\n",
      "\n",
      " 16         130 LOAD_NAME                4 (team)\n",
      "            132 LOAD_NAME                5 (Team)\n",
      "            134 LOAD_ATTR                7 (WHITE)\n",
      "            136 COMPARE_OP               2 (==)\n",
      "            138 POP_JUMP_IF_FALSE      146\n",
      "\n",
      " 17         140 LOAD_CONST               5 (1)\n",
      "            142 STORE_NAME              17 (forward)\n",
      "            144 JUMP_FORWARD             4 (to 150)\n",
      "\n",
      " 19     >>  146 LOAD_CONST               6 (-1)\n",
      "            148 STORE_NAME              17 (forward)\n",
      "\n",
      " 22     >>  150 LOAD_NAME               18 (check_space_wrapper)\n",
      "            152 LOAD_NAME               15 (row)\n",
      "            154 LOAD_NAME               17 (forward)\n",
      "            156 BINARY_ADD\n",
      "            158 LOAD_NAME               16 (col)\n",
      "            160 LOAD_CONST               5 (1)\n",
      "            162 BINARY_ADD\n",
      "            164 LOAD_NAME                2 (board_size)\n",
      "            166 CALL_FUNCTION            3\n",
      "            168 LOAD_NAME                8 (opp_team)\n",
      "            170 COMPARE_OP               2 (==)\n",
      "            172 POP_JUMP_IF_FALSE      234\n",
      "\n",
      " 23         174 LOAD_NAME               19 (capture)\n",
      "            176 LOAD_NAME               15 (row)\n",
      "            178 LOAD_NAME               17 (forward)\n",
      "            180 BINARY_ADD\n",
      "            182 LOAD_NAME               16 (col)\n",
      "            184 LOAD_CONST               5 (1)\n",
      "            186 BINARY_ADD\n",
      "            188 CALL_FUNCTION            2\n",
      "            190 POP_TOP\n",
      "\n",
      " 24         192 LOAD_NAME                0 (dlog)\n",
      "            194 LOAD_CONST               7 ('Captured at: (')\n",
      "            196 LOAD_NAME                9 (str)\n",
      "            198 LOAD_NAME               15 (row)\n",
      "            200 LOAD_NAME               17 (forward)\n",
      "            202 BINARY_ADD\n",
      "            204 CALL_FUNCTION            1\n",
      "            206 BINARY_ADD\n",
      "            208 LOAD_CONST               8 (', ')\n",
      "            210 BINARY_ADD\n",
      "            212 LOAD_NAME                9 (str)\n",
      "            214 LOAD_NAME               16 (col)\n",
      "            216 LOAD_CONST               5 (1)\n",
      "            218 BINARY_ADD\n",
      "            220 CALL_FUNCTION            1\n",
      "            222 BINARY_ADD\n",
      "            224 LOAD_CONST               9 (')')\n",
      "            226 BINARY_ADD\n",
      "            228 CALL_FUNCTION            1\n",
      "            230 POP_TOP\n",
      "            232 JUMP_FORWARD           146 (to 380)\n",
      "\n",
      " 26     >>  234 LOAD_NAME               18 (check_space_wrapper)\n",
      "            236 LOAD_NAME               15 (row)\n",
      "            238 LOAD_NAME               17 (forward)\n",
      "            240 BINARY_ADD\n",
      "            242 LOAD_NAME               16 (col)\n",
      "            244 LOAD_CONST               5 (1)\n",
      "            246 BINARY_SUBTRACT\n",
      "            248 LOAD_NAME                2 (board_size)\n",
      "            250 CALL_FUNCTION            3\n",
      "            252 LOAD_NAME                8 (opp_team)\n",
      "            254 COMPARE_OP               2 (==)\n",
      "            256 EXTENDED_ARG             1\n",
      "            258 POP_JUMP_IF_FALSE      320\n",
      "\n",
      " 27         260 LOAD_NAME               19 (capture)\n",
      "            262 LOAD_NAME               15 (row)\n",
      "            264 LOAD_NAME               17 (forward)\n",
      "            266 BINARY_ADD\n",
      "            268 LOAD_NAME               16 (col)\n",
      "            270 LOAD_CONST               5 (1)\n",
      "            272 BINARY_SUBTRACT\n",
      "            274 CALL_FUNCTION            2\n",
      "            276 POP_TOP\n",
      "\n",
      " 28         278 LOAD_NAME                0 (dlog)\n",
      "            280 LOAD_CONST               7 ('Captured at: (')\n",
      "            282 LOAD_NAME                9 (str)\n",
      "            284 LOAD_NAME               15 (row)\n",
      "            286 LOAD_NAME               17 (forward)\n",
      "            288 BINARY_ADD\n",
      "            290 CALL_FUNCTION            1\n",
      "            292 BINARY_ADD\n",
      "            294 LOAD_CONST               8 (', ')\n",
      "            296 BINARY_ADD\n",
      "            298 LOAD_NAME                9 (str)\n",
      "            300 LOAD_NAME               16 (col)\n",
      "            302 LOAD_CONST               5 (1)\n",
      "            304 BINARY_SUBTRACT\n",
      "            306 CALL_FUNCTION            1\n",
      "            308 BINARY_ADD\n",
      "            310 LOAD_CONST               9 (')')\n",
      "            312 BINARY_ADD\n",
      "            314 CALL_FUNCTION            1\n",
      "            316 POP_TOP\n",
      "            318 JUMP_FORWARD            60 (to 380)\n",
      "\n",
      " 31     >>  320 LOAD_NAME               15 (row)\n",
      "            322 LOAD_NAME               17 (forward)\n",
      "            324 BINARY_ADD\n",
      "            326 LOAD_CONST               6 (-1)\n",
      "            328 COMPARE_OP               3 (!=)\n",
      "            330 EXTENDED_ARG             1\n",
      "            332 POP_JUMP_IF_FALSE      500\n",
      "            334 LOAD_NAME               15 (row)\n",
      "            336 LOAD_NAME               17 (forward)\n",
      "            338 BINARY_ADD\n",
      "            340 LOAD_NAME                2 (board_size)\n",
      "            342 COMPARE_OP               3 (!=)\n",
      "            344 EXTENDED_ARG             1\n",
      "            346 POP_JUMP_IF_FALSE      500\n",
      "            348 LOAD_NAME               18 (check_space_wrapper)\n",
      "            350 LOAD_NAME               15 (row)\n",
      "            352 LOAD_NAME               17 (forward)\n",
      "            354 BINARY_ADD\n",
      "            356 LOAD_NAME               16 (col)\n",
      "            358 LOAD_NAME                2 (board_size)\n",
      "            360 CALL_FUNCTION            3\n",
      "            362 EXTENDED_ARG             1\n",
      "            364 POP_JUMP_IF_TRUE       500\n",
      "\n",
      " 33         366 LOAD_NAME               20 (move_forward)\n",
      "            368 CALL_FUNCTION            0\n",
      "            370 POP_TOP\n",
      "\n",
      " 34         372 LOAD_NAME                0 (dlog)\n",
      "            374 LOAD_CONST              10 ('Moved forward!')\n",
      "            376 CALL_FUNCTION            1\n",
      "            378 POP_TOP\n",
      "        >>  380 JUMP_FORWARD           118 (to 500)\n",
      "\n",
      " 40     >>  382 LOAD_NAME                4 (team)\n",
      "            384 LOAD_NAME                5 (Team)\n",
      "            386 LOAD_ATTR                7 (WHITE)\n",
      "            388 COMPARE_OP               2 (==)\n",
      "            390 EXTENDED_ARG             1\n",
      "            392 POP_JUMP_IF_FALSE      400\n",
      "\n",
      " 41         394 LOAD_CONST              11 (0)\n",
      "            396 STORE_NAME              21 (index)\n",
      "            398 JUMP_FORWARD             8 (to 408)\n",
      "\n",
      " 43     >>  400 LOAD_NAME                2 (board_size)\n",
      "            402 LOAD_CONST               5 (1)\n",
      "            404 BINARY_SUBTRACT\n",
      "            406 STORE_NAME              21 (index)\n",
      "\n",
      " 45     >>  408 SETUP_LOOP              90 (to 500)\n",
      "            410 LOAD_NAME               22 (range)\n",
      "            412 LOAD_NAME                2 (board_size)\n",
      "            414 CALL_FUNCTION            1\n",
      "            416 GET_ITER\n",
      "        >>  418 FOR_ITER                78 (to 498)\n",
      "            420 STORE_NAME              23 (_)\n",
      "\n",
      " 46         422 LOAD_NAME               24 (random)\n",
      "            424 LOAD_METHOD             25 (randint)\n",
      "            426 LOAD_CONST              11 (0)\n",
      "            428 LOAD_NAME                2 (board_size)\n",
      "            430 LOAD_CONST               5 (1)\n",
      "            432 BINARY_SUBTRACT\n",
      "            434 CALL_METHOD              2\n",
      "            436 STORE_NAME              26 (i)\n",
      "\n",
      " 47         438 LOAD_NAME               27 (check_space)\n",
      "            440 LOAD_NAME               21 (index)\n",
      "            442 LOAD_NAME               26 (i)\n",
      "            444 CALL_FUNCTION            2\n",
      "            446 EXTENDED_ARG             1\n",
      "            448 POP_JUMP_IF_TRUE       418\n",
      "\n",
      " 48         450 LOAD_NAME               28 (spawn)\n",
      "            452 LOAD_NAME               21 (index)\n",
      "            454 LOAD_NAME               26 (i)\n",
      "            456 CALL_FUNCTION            2\n",
      "            458 POP_TOP\n",
      "\n",
      " 49         460 LOAD_NAME                0 (dlog)\n",
      "            462 LOAD_CONST              12 ('Spawned unit at: (')\n",
      "            464 LOAD_NAME                9 (str)\n",
      "            466 LOAD_NAME               21 (index)\n",
      "            468 CALL_FUNCTION            1\n",
      "            470 BINARY_ADD\n",
      "            472 LOAD_CONST               8 (', ')\n",
      "            474 BINARY_ADD\n",
      "            476 LOAD_NAME                9 (str)\n",
      "            478 LOAD_NAME               26 (i)\n",
      "            480 CALL_FUNCTION            1\n",
      "            482 BINARY_ADD\n",
      "            484 LOAD_CONST               9 (')')\n",
      "            486 BINARY_ADD\n",
      "            488 CALL_FUNCTION            1\n",
      "            490 POP_TOP\n",
      "\n",
      " 50         492 BREAK_LOOP\n",
      "            494 EXTENDED_ARG             1\n",
      "            496 JUMP_ABSOLUTE          418\n",
      "        >>  498 POP_BLOCK\n",
      "\n",
      " 52     >>  500 LOAD_NAME               29 (get_bytecode)\n",
      "            502 CALL_FUNCTION            0\n",
      "            504 STORE_NAME              30 (bytecode)\n",
      "\n",
      " 53         506 LOAD_NAME                0 (dlog)\n",
      "            508 LOAD_CONST              13 ('Done! Bytecode left: ')\n",
      "            510 LOAD_NAME                9 (str)\n",
      "            512 LOAD_NAME               30 (bytecode)\n",
      "            514 CALL_FUNCTION            1\n",
      "            516 BINARY_ADD\n",
      "            518 CALL_FUNCTION            1\n",
      "            520 POP_TOP\n",
      "            522 LOAD_CONST              14 (None)\n",
      "            524 RETURN_VALUE\n"
     ]
    }
   ],
   "source": [
    "dis.dis(examplefuncs)"
   ]
  },
  {
   "cell_type": "code",
   "execution_count": 69,
   "metadata": {},
   "outputs": [],
   "source": [
    "a = list(dis.get_instructions(examplefuncs))"
   ]
  },
  {
   "cell_type": "code",
   "execution_count": 70,
   "metadata": {},
   "outputs": [],
   "source": [
    "for ix,i in enumerate(a[:]):\n",
    "    a[ix] = Instruction(i)"
   ]
  },
  {
   "cell_type": "code",
   "execution_count": 71,
   "metadata": {},
   "outputs": [],
   "source": [
    "iss = [i for i in a if i.opcode == 143]"
   ]
  },
  {
   "cell_type": "code",
   "execution_count": 72,
   "metadata": {},
   "outputs": [
    {
     "data": {
      "text/plain": [
       "[]"
      ]
     },
     "execution_count": 72,
     "metadata": {},
     "output_type": "execute_result"
    }
   ],
   "source": [
    "iss"
   ]
  },
  {
   "cell_type": "code",
   "execution_count": 73,
   "metadata": {},
   "outputs": [
    {
     "data": {
      "text/plain": [
       "[93, 110, 120, 121, 122, 143, 154]"
      ]
     },
     "execution_count": 73,
     "metadata": {},
     "output_type": "execute_result"
    }
   ],
   "source": [
    "dis.hasjrel"
   ]
  },
  {
   "cell_type": "code",
   "execution_count": 74,
   "metadata": {},
   "outputs": [
    {
     "data": {
      "text/plain": [
       "101"
      ]
     },
     "execution_count": 74,
     "metadata": {},
     "output_type": "execute_result"
    }
   ],
   "source": [
    "a[0].opcode"
   ]
  },
  {
   "cell_type": "code",
   "execution_count": null,
   "metadata": {},
   "outputs": [],
   "source": []
  }
 ],
 "metadata": {
  "@webio": {
   "lastCommId": null,
   "lastKernelId": null
  },
  "kernelspec": {
   "display_name": "Python 3",
   "language": "python",
   "name": "python3"
  },
  "language_info": {
   "codemirror_mode": {
    "name": "ipython",
    "version": 3
   },
   "file_extension": ".py",
   "mimetype": "text/x-python",
   "name": "python",
   "nbconvert_exporter": "python",
   "pygments_lexer": "ipython3",
   "version": "3.7.6"
  }
 },
 "nbformat": 4,
 "nbformat_minor": 2
}
